Workbook

Sheet Requirement Overview
A1: Aging | B1: Type of Hire | C1: Job ID | D1: Job Posted Date | E1: Business Unit | F1: Department | G1: Client | H1: Domain | I1: Position | J1: Priority | K1: Number of Openings | L1: Position Current Status | M1: Remarks | N1: Candidate Concerned | O1: Date of Hold | P1: Date of Offer Stage | Q1: Date of Offer | R1: Date of Joining | S1: CTC of Candidate | T1: Source | U1: Harmonized Role | V1: Recruiter tagged | W1: Original Job Post Date
A2: =IF(OR(L2="Closed",L2="Offered"),Q2-D2,TODAY()-D2) -> 163 | B2: New | C2: A001 | D2: 45976 | E2: Talme | G2: EMIDS | H2: IT | I2: Python Developer | J2: High | K2: 2 | L2: Open
A3: =IF(OR(L3="Closed",L3="Offered"),Q3-D3,TODAY()-D3) -> 163 | B3: New | C3: A002 | D3: 45976 | E3: Talme | G3: EMIDS | H3: IT | I3: Lead Data Engineer | J3: High | K3: 4 | L3: Open
A4: =IF(OR(L4="Closed",L4="Offered"),Q4-D4,TODAY()-D4) -> 163 | B4: New | C4: A003 | D4: 45976 | E4: Talme | G4: EMIDS | H4: IT | I4: Python Architect | J4: High | K4: 1 | L4: Open
A5: =IF(OR(L5="Closed",L5="Offered"),Q5-D5,TODAY()-D5) -> 163 | B5: New | C5: A004 | D5: 45976 | E5: Talme | G5: EMIDS | H5: IT | I5: Windows system adminstrator | J5: High | K5: 1 | L5: Open
A6: =IF(OR(L6="Closed",L6="Offered"),Q6-D6,TODAY()-D6) -> 187 | B6: New | C6: B001 | D6: 45952 | E6: Talme | G6: KPIT | H6: IT | I6: Android BSP Developer | J6: High | K6: 2 | L6: Open
A7: =IF(OR(L7="Closed",L7="Offered"),Q7-D7,TODAY()-D7) -> 187 | B7: New | C7: B002 | D7: 45952 | E7: Talme | G7: KPIT | H7: IT | I7: Display driver | J7: High | K7: 1 | L7: Open
A8: =IF(OR(L8="Closed",L8="Offered"),Q8-D8,TODAY()-D8) -> 187 | B8: New | C8: B003 | D8: 45952 | E8: Talme | G8: KPIT | H8: IT | I8: Audio Driver | J8: High | K8: 1 | L8: Open
A9: =IF(OR(L9="Closed",L9="Offered"),Q9-D9,TODAY()-D9) -> 187 | B9: New | C9: C001 | D9: 45952 | E9: Talme | G9: Thoughtfocus | H9: IT | I9: Data Delivery Manager | J9: High | K9: 1 | L9: Open
A10: =IF(OR(L10="Closed",L10="Offered"),Q10-D10,TODAY()-D10) -> 187 | B10: New | C10: C002 | D10: 45952 | E10: Talme | G10: Thoughtfocus | H10: IT | I10: Senior IAM Operation Engineer | J10: High | K10: 1 | L10: Open
A11: =IF(OR(L11="Closed",L11="Offered"),Q11-D11,TODAY()-D11) -> 187 | B11: New | C11: C003 | D11: 45952 | E11: Talme | G11: Thoughtfocus | H11: IT | I11: Lead IAM Management | J11: High | K11: 1 | L11: Open
A12: =IF(OR(L12="Closed",L12="Offered"),Q12-D12,TODAY()-D12) -> 187 | B12: New | C12: C004 | D12: 45952 | E12: Talme | G12: Thoughtfocus | H12: IT | I12: PERL Developer | J12: Low | K12: 18 | L12: Hold
A13: =IF(OR(L13="Closed",L13="Offered"),Q13-D13,TODAY()-D13) -> 117 | B13: New | C13: D001 | D13: 46022 | E13: Talme | G13: Peritas | H13: Non - IT | I13: Inside Sales Executive | J13: High | K13: 3 | L13: Open
... A30: =IF(OR(L30="Closed",L30="Offered"),Q30-D30,TODAY()-D30) -> 98 | B30: New | C30: H006 | D30: 46041 | E30: Talme | G30: LeadSOC | H30: IT | I30: Analog RF Designer | J30: High | K30: 1 | L30: Open
A31: =IF(OR(L31="Closed",L31="Offered"),Q31-D31,TODAY()-D31) -> 14 | B31: New | C31: H007 | D31: 46016 | E31: Talme | G31: GNA | H31: IT | I31: Web Designer | J31: High | K31: 1 | L31: Closed | N31: Bhageesha | Q31: 46030 | R31: 46038 | S31: 3.58 LPA | T31: Portal-Naukri | V31: Harshitha
A32: =IF(OR(L32="Closed",L32="Offered"),Q32-D32,TODAY()-D32) -> 187 | B32: New | C32: H008 | D32: 45952 | E32: Talme | G32: Thoughtfocus | H32: IT | I32: IAM Engineer Professionals | J32: High | K32: 1 | L32: Open
A33: =IF(OR(L33="Closed",L33="Offered"),Q33-D33,TODAY()-D33) -> 289 | B33: New | C33: H009 | D33: 45850 | E33: Talme | G33: Semnox Solutions | H33: IT | I33: .Net Backend Developer | J33: High | K33: 1 | L33: Open
A34: =IF(OR(L34="Closed",L34="Offered"),Q34-D34,TODAY()-D34) -> 94 | B34: New | C34: H010 | D34: 46045 | E34: Talme | G34: Semnox Solutions | H34: IT | I34: Technical Lead - Mobile Development | J34: High | K34: 3 | L34: Open
A35: =IF(OR(L35="Closed",L35="Offered"),Q35-D35,TODAY()-D35) -> 94 | B35: New | C35: H011 | D35: 46045 | E35: Talme | G35: Prasanna Technologies | H35: IT | I35: .Net Developer - Contract Role | J35: High | K35: 1 | L35: Hold
A36: =IF(OR(L36="Closed",L36="Offered"),Q36-D36,TODAY()-D36) -> 93 | B36: New | C36: H012 | D36: 46046 | E36: Talme | G36: Viditha | H36: IT | I36: Developer - Angular & Node Js | J36: High | K36: 1 | L36: Open
A37: =IF(OR(L37="Closed",L37="Offered"),Q37-D37,TODAY()-D37) -> 90 | B37: New | C37: H013 | D37: 46049 | E37: Talme | G37: Thoughtfocus | H37: IT | I37: Java Lead Analyst | J37: High | K37: 1 | L37: Open
A38: =IF(OR(L38="Closed",L38="Offered"),Q38-D38,TODAY()-D38) -> 87 | B38: New | C38: H014 | D38: 46052 | E38: Talme | G38: EMIDS | H38: IT | I38: Java Script Developer | J38: High | K38: 1 | L38: Open
A39: =IF(OR(L39="Closed",L39="Offered"),Q39-D39,TODAY()-D39) -> 87 | B39: New | C39: I001 | D39: 46052 | E39: Talme | G39: GNA | H39: IT | I39: QA Analyst | J39: High | K39: 1 | L39: Open
A40: =IF(OR(L40="Closed",L40="Offered"),Q40-D40,TODAY()-D40) -> 87 | B40: New | C40: I002 | D40: 46052 | E40: Talme | G40: GNA | H40: IT | I40: Full Stack Developer | J40: High | K40: 1 | L40: Open
A41: =IF(OR(L41="Closed",L41="Offered"),Q41-D41,TODAY()-D41) -> 75 | B41: New | C41: I003 | D41: 46064 | E41: Talme | G41: Thoughtfocus | H41: IT | I41: Full Stack Developer | J41: High | K41: 3 | L41: Open
A42: =IF(OR(L42="Closed",L42="Offered"),Q42-D42,TODAY()-D42) -> 75 | B42: New | C42: I004 | D42: 46064 | E42: Talme | G42: Thoughtfocus | H42: IT | I42: Backend developer | J42: High | K42: 3 | L42: Open
A43: =IF(OR(L43="Closed",L43="Offered"),Q43-D43,TODAY()-D43) -> 75 | B43: New | C43: I005 | D43: 46064 | E43: Talme | G43: Thoughtfocus | H43: IT | I43: Front end developer | J43: High | K43: 3 | L43: Open
... A73: =IF(OR(L73="Closed",L73="Offered"),Q73-D73,TODAY()-D73) -> 20 | B73: New | C73: P001 | D73: 46119 | E73: Talme | G73: LTTS | H73: IT | I73: Software Engineer | J73: High | K73: 1 | L73: Open

Sheet Candidate Master
A1: Job Id | B1: Recruiter Id | C1: Recruiter Name | D1: Business Unit | E1: Domain | F1: Position | G1: Client | H1: Candidate Name | I1: Notice Period | J1: Candidate Email | K1: Phone No. | L1: Qualification | M1: Years of Exp | N1: Previous Company | O1: Previous CTC | P1: Location | Q1: Prefered Location | R1: Expected CTC | S1: Candidate Current Status | T1: Source | U1: Source Date | V1: Screening Date | W1: Screening Notes | X1: Tech 1 date | Y1: Tech 1 Status | Z1: Tech 1 Remarks | AA1: Tech 1 Panel | AB1: Tech 2 date | AC1: Tech 2 Status | AD1: Tech 2 Remarks | AE1: Tech 2 Panel | AF1: Tech 3 date | AG1: Tech 3 Status | AH1: Tech 3 Remarks | AI1: Tech 3 Panel | AJ1: Offer Stage Input date | AK1: Date of Document Collection | AL1: Date of Approval | AM1: Offer Date | AN1: Offer Status | AO1: Date of Offer Accept/Reject | AP1: Offer Accept Status | AQ1: Date Of Joining | AR1: Joining Status | AS1: CTC Offered
A2: B001 | B2: R004 | C2: Pooja | D2: =IF(ISBLANK(A2),"",_xlfn.XLOOKUP(A2,'Requirement Overview'!C:C,'Requirement Overview'!E:E)) -> Talme | E2: IT | F2: =IF(ISBLANK(A2),"",_xlfn.XLOOKUP(A2,'Requirement Overview'!C:C,'Requirement Overview'!I:I)) -> Android BSP Developer | G2: KPIT | H2: DINESHKUMAR S | K2: 6383142221 | M2: 5.11 | O2: 12 | R2: 18 | S2: Screening Reject | T2: Portal-Naukri | U2: 46028 | V2: 46028
A3: B001 | B3: R004 | C3: Pooja | D3: Talme | E3: =IF(ISBLANK(A3),"",_xlfn.XLOOKUP(A3,'Requirement Overview'!C:C,'Requirement Overview'!H:H)) -> IT | F3: =IF(ISBLANK(A3),"",_xlfn.XLOOKUP(A3,'Requirement Overview'!C:C,'Requirement Overview'!I:I)) -> Android BSP Developer | G3: KPIT | H3: Siva Raj Mahendrakar | K3: 9985736277 | S3: Screening Reject | T3: Portal-Naukri | U3: 46028 | V3: 46028
A4: B001 | B4: R004 | C4: Pooja | D4: Talme | E4: =IF(ISBLANK(A4),"",_xlfn.XLOOKUP(A4,'Requirement Overview'!C:C,'Requirement Overview'!H:H)) -> IT | F4: =IF(ISBLANK(A4),"",_xlfn.XLOOKUP(A4,'Requirement Overview'!C:C,'Requirement Overview'!I:I)) -> Android BSP Developer | G4: KPIT | H4: K Mallikarjuna Rao | J4: malli.k1117@gmail.com | K4: 9642601689 | M4: 6.8 | O4: 23 | R4: 30% Hike | S4: Screening Reject | T4: Portal-Naukri | U4: 46028 | V4: 46028
A5: B001 | B5: R004 | C5: Pooja | D5: Talme | E5: =IF(ISBLANK(A5),"",_xlfn.XLOOKUP(A5,'Requirement Overview'!C:C,'Requirement Overview'!H:H)) -> IT | F5: =IF(ISBLANK(A5),"",_xlfn.XLOOKUP(A5,'Requirement Overview'!C:C,'Requirement Overview'!I:I)) -> Android BSP Developer | G5: KPIT | H5: Gopi Vagga | K5: 9845892797 | M5: 12 | O5: 18.5 | R5: 25 | S5: Screening Reject | T5: Portal-Naukri | U5: 46028 | V5: 46028
A6: B001 | B6: R004 | C6: Pooja | D6: Talme | E6: =IF(ISBLANK(A6),"",_xlfn.XLOOKUP(A6,'Requirement Overview'!C:C,'Requirement Overview'!H:H)) -> IT | F6: =IF(ISBLANK(A6),"",_xlfn.XLOOKUP(A6,'Requirement Overview'!C:C,'Requirement Overview'!I:I)) -> Android BSP Developer | G6: KPIT | H6: Priyankka K | K6: 9618943124 | M6: 10.8 | O6: 22.5 | R6: 32 | S6: Screening Reject | T6: Portal-Naukri | U6: 46028 | V6: 46028
A7: B001 | B7: R004 | C7: Pooja | D7: Talme | E7: =IF(ISBLANK(A7),"",_xlfn.XLOOKUP(A7,'Requirement Overview'!C:C,'Requirement Overview'!H:H)) -> IT | F7: =IF(ISBLANK(A7),"",_xlfn.XLOOKUP(A7,'Requirement Overview'!C:C,'Requirement Overview'!I:I)) -> Android BSP Developer | G7: KPIT | H7: Tanmay Desai | K7: 7567041466 | S7: Screening Reject | T7: Portal-Naukri | U7: 46028 | V7: 46028
A8: B001 | B8: R004 | C8: =IF(ISBLANK(B8),"",_xlfn.XLOOKUP(B8,Recruiter!A:A,Recruiter!B:B)) -> Pooja | D8: Talme | E8: =IF(ISBLANK(A8),"",_xlfn.XLOOKUP(A8,'Requirement Overview'!C:C,'Requirement Overview'!H:H)) -> IT | F8: =IF(ISBLANK(A8),"",_xlfn.XLOOKUP(A8,'Requirement Overview'!C:C,'Requirement Overview'!I:I)) -> Android BSP Developer | G8: KPIT | H8: Mohamed musthafa AV | K8: 9895080216 | S8: Screening Reject | T8: Portal-Naukri | U8: 46029 | V8: 46029
A9: B001 | B9: R004 | C9: =IF(ISBLANK(B9),"",_xlfn.XLOOKUP(B9,Recruiter!A:A,Recruiter!B:B)) -> Pooja | D9: Talme | E9: =IF(ISBLANK(A9),"",_xlfn.XLOOKUP(A9,'Requirement Overview'!C:C,'Requirement Overview'!H:H)) -> IT | F9: =IF(ISBLANK(A9),"",_xlfn.XLOOKUP(A9,'Requirement Overview'!C:C,'Requirement Overview'!I:I)) -> Android BSP Developer | G9: KPIT | H9: Manikandan R | K9: 9500383529 | S9: Screening Reject | T9: Portal-Naukri | U9: 46029 | V9: 46029
A10: B001 | B10: R004 | C10: =IF(ISBLANK(B10),"",_xlfn.XLOOKUP(B10,Recruiter!A:A,Recruiter!B:B)) -> Pooja | D10: Talme | E10: =IF(ISBLANK(A10),"",_xlfn.XLOOKUP(A10,'Requirement Overview'!C:C,'Requirement Overview'!H:H)) -> IT | F10: =IF(ISBLANK(A10),"",_xlfn.XLOOKUP(A10,'Requirement Overview'!C:C,'Requirement Overview'!I:I)) -> Android BSP Developer | G10: KPIT | H10: Lavhate Pranav Pralhad | K10: 9021483838 | S10: Screening Reject | T10: Portal-Naukri | U10: 46029 | V10: 46029
A11: B001 | B11: R004 | C11: =IF(ISBLANK(B11),"",_xlfn.XLOOKUP(B11,Recruiter!A:A,Recruiter!B:B)) -> Pooja | D11: Talme | E11: =IF(ISBLANK(A11),"",_xlfn.XLOOKUP(A11,'Requirement Overview'!C:C,'Requirement Overview'!H:H)) -> IT | F11: =IF(ISBLANK(A11),"",_xlfn.XLOOKUP(A11,'Requirement Overview'!C:C,'Requirement Overview'!I:I)) -> Android BSP Developer | G11: KPIT | H11: Mayur Barapatre | J11: mayur04barapatre@gmail.com | K11: 6281643063 | O11: 20 | R11: 28 | S11: Screening Reject | T11: Portal-Naukri | U11: 46029 | V11: 46029
A12: B001 | B12: R004 | C12: =IF(ISBLANK(B12),"",_xlfn.XLOOKUP(B12,Recruiter!A:A,Recruiter!B:B)) -> Pooja | D12: Talme | E12: =IF(ISBLANK(A12),"",_xlfn.XLOOKUP(A12,'Requirement Overview'!C:C,'Requirement Overview'!H:H)) -> IT | F12: =IF(ISBLANK(A12),"",_xlfn.XLOOKUP(A12,'Requirement Overview'!C:C,'Requirement Overview'!I:I)) -> Android BSP Developer | G12: KPIT | H12: Naveen kumar | K12: 7981241891 | S12: Screening Reject | T12: Portal-Naukri | U12: 46029 | V12: 46029
A13: B001 | B13: R004 | C13: =IF(ISBLANK(B13),"",_xlfn.XLOOKUP(B13,Recruiter!A:A,Recruiter!B:B)) -> Pooja | D13: Talme | E13: =IF(ISBLANK(A13),"",_xlfn.XLOOKUP(A13,'Requirement Overview'!C:C,'Requirement Overview'!H:H)) -> IT | F13: =IF(ISBLANK(A13),"",_xlfn.XLOOKUP(A13,'Requirement Overview'!C:C,'Requirement Overview'!I:I)) -> Android BSP Developer | G13: KPIT | H13: Naveen Raj | J13: naveenraj5341@gmail.com | K13: 9400603341 | O13: 26.7 | R13: 36 | S13: Screening Reject | T13: Portal-Naukri | U13: 46029 | V13: 46029
A14: B001 | B14: R004 | C14: =IF(ISBLANK(B14),"",_xlfn.XLOOKUP(B14,Recruiter!A:A,Recruiter!B:B)) -> Pooja | D14: Talme | E14: =IF(ISBLANK(A14),"",_xlfn.XLOOKUP(A14,'Requirement Overview'!C:C,'Requirement Overview'!H:H)) -> IT | F14: =IF(ISBLANK(A14),"",_xlfn.XLOOKUP(A14,'Requirement Overview'!C:C,'Requirement Overview'!I:I)) -> Android BSP Developer | G14: KPIT | H14: Vrushabh Rangraoji Motghare | K14: 9689959406 | S14: Screening Reject | T14: Portal-Naukri | U14: 46029 | V14: 46029
A15: B001 | B15: R004 | C15: =IF(ISBLANK(B15),"",_xlfn.XLOOKUP(B15,Recruiter!A:A,Recruiter!B:B)) -> Pooja | D15: =IF(ISBLANK(A15),"",_xlfn.XLOOKUP(A15,'Requirement Overview'!C:C,'Requirement Overview'!E:E)) -> Talme | E15: IT | F15: =IF(ISBLANK(A15),"",_xlfn.XLOOKUP(A15,'Requirement Overview'!C:C,'Requirement Overview'!I:I)) -> Android BSP Developer | G15: =IF(ISBLANK(A15),"",_xlfn.XLOOKUP(A15,'Requirement Overview'!C:C,'Requirement Overview'!G:G)) -> KPIT | H15: Mosin Inamadar | K15: 9767204706 | S15: Screening Reject | T15: Portal-Naukri | U15: 46029 | V15: 46029
A16: H001 | B16: R003 | C16: Bhoomika | D16: =IF(ISBLANK(A16),"",_xlfn.XLOOKUP(A16,'Requirement Overview'!C:C,'Requirement Overview'!E:E)) -> Talme | E16: =IF(ISBLANK(A16),"",_xlfn.XLOOKUP(A16,'Requirement Overview'!C:C,'Requirement Overview'!H:H)) -> Non - IT | F16: =IF(ISBLANK(A16),"",_xlfn.XLOOKUP(A16,'Requirement Overview'!C:C,'Requirement Overview'!I:I)) -> Business developement executive | G16: Saralx | H16: Alefiyah Naib | I16: 30 Days | J16: alefiyahnaib515253@gmail.com | K16: 9179265452 | L16: B.ED | M16: 1.5 Years | N16: GIT Academy, Bengaluru | O16: 2.9 LPA | P16: Bengaluru | Q16: Bengaluru | R16: 3.9 LPA | S16: Screening Reject by Client | T16: Portal-LinkedIN | U16: 46029 | V16: 46029
A17: H001 | B17: R003 | C17: Bhoomika | D17: =IF(ISBLANK(A17),"",_xlfn.XLOOKUP(A17,'Requirement Overview'!C:C,'Requirement Overview'!E:E)) -> Talme | E17: =IF(ISBLANK(A17),"",_xlfn.XLOOKUP(A17,'Requirement Overview'!C:C,'Requirement Overview'!H:H)) -> Non - IT | F17: =IF(ISBLANK(A17),"",_xlfn.XLOOKUP(A17,'Requirement Overview'!C:C,'Requirement Overview'!I:I)) -> Business developement executive | G17: Saralx | H17: Ranjitha N | K17: 9535544283 | S17: Screening Reject | T17: Portal-LinkedIN | U17: 46028 | V17: 46028
A18: H001 | B18: R003 | C18: Bhoomika | D18: =IF(ISBLANK(A18),"",_xlfn.XLOOKUP(A18,'Requirement Overview'!C:C,'Requirement Overview'!E:E)) -> Talme | E18: =IF(ISBLANK(A18),"",_xlfn.XLOOKUP(A18,'Requirement Overview'!C:C,'Requirement Overview'!H:H)) -> Non - IT | F18: =IF(ISBLANK(A18),"",_xlfn.XLOOKUP(A18,'Requirement Overview'!C:C,'Requirement Overview'!I:I)) -> Business developement executive | G18: Saralx | H18: Dimpu B | K18: 9535735939 | S18: Screening Reject | T18: Portal-LinkedIN | U18: 46028 | V18: 46028
A19: H001 | B19: R003 | C19: Bhoomika | D19: =IF(ISBLANK(A19),"",_xlfn.XLOOKUP(A19,'Requirement Overview'!C:C,'Requirement Overview'!E:E)) -> Talme | E19: =IF(ISBLANK(A19),"",_xlfn.XLOOKUP(A19,'Requirement Overview'!C:C,'Requirement Overview'!H:H)) -> Non - IT | F19: =IF(ISBLANK(A19),"",_xlfn.XLOOKUP(A19,'Requirement Overview'!C:C,'Requirement Overview'!I:I)) -> Business developement executive | G19: Saralx | H19: Niveditha S | K19: 7760182939 | S19: Screening Reject | T19: Portal-LinkedIN | U19: 46028 | V19: 46028
A20: H001 | B20: R003 | C20: Bhoomika | D20: =IF(ISBLANK(A20),"",_xlfn.XLOOKUP(A20,'Requirement Overview'!C:C,'Requirement Overview'!E:E)) -> Talme | E20: =IF(ISBLANK(A20),"",_xlfn.XLOOKUP(A20,'Requirement Overview'!C:C,'Requirement Overview'!H:H)) -> Non - IT | F20: =IF(ISBLANK(A20),"",_xlfn.XLOOKUP(A20,'Requirement Overview'!C:C,'Requirement Overview'!I:I)) -> Business developement executive | G20: Saralx | H20: Dileep Kumar R | K20: 6364919558 | S20: Screening Reject | T20: Portal-LinkedIN | U20: 46028 | V20: 46028
A21: H001 | B21: R003 | C21: Bhoomika | D21: =IF(ISBLANK(A21),"",_xlfn.XLOOKUP(A21,'Requirement Overview'!C:C,'Requirement Overview'!E:E)) -> Talme | E21: =IF(ISBLANK(A21),"",_xlfn.XLOOKUP(A21,'Requirement Overview'!C:C,'Requirement Overview'!H:H)) -> Non - IT | F21: =IF(ISBLANK(A21),"",_xlfn.XLOOKUP(A21,'Requirement Overview'!C:C,'Requirement Overview'!I:I)) -> Business developement executive | G21: Saralx | H21: Harshita Khanna | K21: 8860765049 | S21: Screening Reject | T21: Portal-LinkedIN | U21: 46028 | V21: 46028
A22: H001 | B22: R003 | C22: Bhoomika | D22: =IF(ISBLANK(A22),"",_xlfn.XLOOKUP(A22,'Requirement Overview'!C:C,'Requirement Overview'!E:E)) -> Talme | E22: =IF(ISBLANK(A22),"",_xlfn.XLOOKUP(A22,'Requirement Overview'!C:C,'Requirement Overview'!H:H)) -> Non - IT | F22: =IF(ISBLANK(A22),"",_xlfn.XLOOKUP(A22,'Requirement Overview'!C:C,'Requirement Overview'!I:I)) -> Business developement executive | G22: Saralx | H22: Nitish Kumar | K22: 6362554577 | S22: Screening Reject | T22: Portal-LinkedIN | U22: 46028 | V22: 46028
A23: H002 | B23: R003 | C23: =IF(ISBLANK(B23),"",_xlfn.XLOOKUP(B23,Recruiter!A:A,Recruiter!B:B)) -> Bhoomika | D23: =IF(ISBLANK(A23),"",_xlfn.XLOOKUP(A23,'Requirement Overview'!C:C,'Requirement Overview'!E:E)) -> Talme | E23: =IF(ISBLANK(A23),"",_xlfn.XLOOKUP(A23,'Requirement Overview'!C:C,'Requirement Overview'!H:H)) -> Non - IT | F23: =IF(ISBLANK(A23),"",_xlfn.XLOOKUP(A23,'Requirement Overview'!C:C,'Requirement Overview'!I:I)) -> Founder office assoicate | G23: Saralx | H23: Shivam Asthana | K23: 6387986418 | M23: 4 Years | O23: 6.24 LPA | R23: 8 lpa | S23: Screening Reject | T23: Portal-LinkedIN | U23: 46027 | V23: 46027
A24: E001 | B24: R004 | C24: =IF(ISBLANK(B24),"",_xlfn.XLOOKUP(B24,Recruiter!A:A,Recruiter!B:B)) -> Pooja | D24: =IF(ISBLANK(A24),"",_xlfn.XLOOKUP(A24,'Requirement Overview'!C:C,'Requirement Overview'!E:E)) -> Talme | E24: =IF(ISBLANK(A24),"",_xlfn.XLOOKUP(A24,'Requirement Overview'!C:C,'Requirement Overview'!H:H)) -> Non - IT | F24: =IF(ISBLANK(A24),"",_xlfn.XLOOKUP(A24,'Requirement Overview'!C:C,'Requirement Overview'!I:I)) -> Graphic Designer | G24: =IF(ISBLANK(A24),"",_xlfn.XLOOKUP(A24,'Requirement Overview'!C:C,'Requirement Overview'!G:G)) -> Avinashi Ads | H24: HARINI YEJJU | J24: yejjuharini42@gmail.com | K24: 9392779274 | S24: Screening Reject | T24: Portal-LinkedIN | U24: 46030 | V24: 46030
A25: E001 | B25: R004 | C25: =IF(ISBLANK(B25),"",_xlfn.XLOOKUP(B25,Recruiter!A:A,Recruiter!B:B)) -> Pooja | D25: =IF(ISBLANK(A25),"",_xlfn.XLOOKUP(A25,'Requirement Overview'!C:C,'Requirement Overview'!E:E)) -> Talme | E25: =IF(ISBLANK(A25),"",_xlfn.XLOOKUP(A25,'Requirement Overview'!C:C,'Requirement Overview'!H:H)) -> Non - IT | F25: =IF(ISBLANK(A25),"",_xlfn.XLOOKUP(A25,'Requirement Overview'!C:C,'Requirement Overview'!I:I)) -> Graphic Designer | G25: =IF(ISBLANK(A25),"",_xlfn.XLOOKUP(A25,'Requirement Overview'!C:C,'Requirement Overview'!G:G)) -> Avinashi Ads | H25: SHRUTI RAI | J25: shrutirai.770@gmail.com | K25: 7704078279 | S25: Screening Reject | T25: Portal-LinkedIN | U25: 46030 | V25: 46030
A26: E001 | B26: R004 | C26: =IF(ISBLANK(B26),"",_xlfn.XLOOKUP(B26,Recruiter!A:A,Recruiter!B:B)) -> Pooja | D26: =IF(ISBLANK(A26),"",_xlfn.XLOOKUP(A26,'Requirement Overview'!C:C,'Requirement Overview'!E:E)) -> Talme | E26: =IF(ISBLANK(A26),"",_xlfn.XLOOKUP(A26,'Requirement Overview'!C:C,'Requirement Overview'!H:H)) -> Non - IT | F26: =IF(ISBLANK(A26),"",_xlfn.XLOOKUP(A26,'Requirement Overview'!C:C,'Requirement Overview'!I:I)) -> Graphic Designer | G26: =IF(ISBLANK(A26),"",_xlfn.XLOOKUP(A26,'Requirement Overview'!C:C,'Requirement Overview'!G:G)) -> Avinashi Ads | H26: Pranathi M.G | J26: pranathigopal00@gmail.com | K26: 8660746114 | S26: Screening Reject | T26: Portal-LinkedIN | U26: 46030 | V26: 46030
A27: D001 | B27: R003 | C27: =IF(ISBLANK(B27),"",_xlfn.XLOOKUP(B27,Recruiter!A:A,Recruiter!B:B)) -> Bhoomika | D27: =IF(ISBLANK(A27),"",_xlfn.XLOOKUP(A27,'Requirement Overview'!C:C,'Requirement Overview'!E:E)) -> Talme | E27: =IF(ISBLANK(A27),"",_xlfn.XLOOKUP(A27,'Requirement Overview'!C:C,'Requirement Overview'!H:H)) -> Non - IT | F27: =IF(ISBLANK(A27),"",_xlfn.XLOOKUP(A27,'Requirement Overview'!C:C,'Requirement Overview'!I:I)) -> Inside Sales Executive | G27: =IF(ISBLANK(A27),"",_xlfn.XLOOKUP(A27,'Requirement Overview'!C:C,'Requirement Overview'!G:G)) -> Peritas | H27: Saloni Sing | I27: 30 Days | J27: salonisingh0877@gmail.com | K27: 6377429482 | L27: MBA | M27: 1.3 Years | N27: Panchami Global Project Pvt Ltd | O27: 2.8 LPA | P27: Bengaluru | Q27: Bengaluru | R27: 3.5 LPA | S27: Screening Reject by Client | T27: Portal-Naukri | U27: 46029 | V27: 46029
A28: D001 | B28: R003 | C28: =IF(ISBLANK(B28),"",_xlfn.XLOOKUP(B28,Recruiter!A:A,Recruiter!B:B)) -> Bhoomika | D28: =IF(ISBLANK(A28),"",_xlfn.XLOOKUP(A28,'Requirement Overview'!C:C,'Requirement Overview'!E:E)) -> Talme | E28: =IF(ISBLANK(A28),"",_xlfn.XLOOKUP(A28,'Requirement Overview'!C:C,'Requirement Overview'!H:H)) -> Non - IT | F28: =IF(ISBLANK(A28),"",_xlfn.XLOOKUP(A28,'Requirement Overview'!C:C,'Requirement Overview'!I:I)) -> Inside Sales Executive | G28: =IF(ISBLANK(A28),"",_xlfn.XLOOKUP(A28,'Requirement Overview'!C:C,'Requirement Overview'!G:G)) -> Peritas | H28: Ashwin N R | I28: 7 Days | J28: dhanyahari878@gmail.com | K28: 7483352201 | L28: P.G.D.C.A | M28: 1.5 Years | N28: Mobility Motors | O28: 2.8 LPA | P28: Bengaluru | Q28: Bengaluru | R28: 3.2 LPA | S28: Screening Reject by Client | T28: Portal-Naukri | U28: 46029 | V28: 46029
A29: D001 | B29: R003 | C29: =IF(ISBLANK(B29),"",_xlfn.XLOOKUP(B29,Recruiter!A:A,Recruiter!B:B)) -> Bhoomika | D29: =IF(ISBLANK(A29),"",_xlfn.XLOOKUP(A29,'Requirement Overview'!C:C,'Requirement Overview'!E:E)) -> Talme | E29: =IF(ISBLANK(A29),"",_xlfn.XLOOKUP(A29,'Requirement Overview'!C:C,'Requirement Overview'!H:H)) -> Non - IT | F29: =IF(ISBLANK(A29),"",_xlfn.XLOOKUP(A29,'Requirement Overview'!C:C,'Requirement Overview'!I:I)) -> Inside Sales Executive | G29: =IF(ISBLANK(A29),"",_xlfn.XLOOKUP(A29,'Requirement Overview'!C:C,'Requirement Overview'!G:G)) -> Peritas | H29: Parul Vishwakarma | I29: 10 Days | J29: parulvishwakarma2020@gmail.com | K29: 8918605535 | L29: B.Tech | M29: 2 Years | N29: Inosystek Solutions Pvt. Ltd | O29: 3.9 LPA | P29: Bengaluru | Q29: Bengaluru | R29: 30% HIKE | S29: Screening Reject by Client | T29: Portal-Naukri | U29: 46029 | V29: 46029
A30: D001 | B30: R003 | C30: =IF(ISBLANK(B30),"",_xlfn.XLOOKUP(B30,Recruiter!A:A,Recruiter!B:B)) -> Bhoomika | D30: =IF(ISBLANK(A30),"",_xlfn.XLOOKUP(A30,'Requirement Overview'!C:C,'Requirement Overview'!E:E)) -> Talme | E30: =IF(ISBLANK(A30),"",_xlfn.XLOOKUP(A30,'Requirement Overview'!C:C,'Requirement Overview'!H:H)) -> Non - IT | F30: =IF(ISBLANK(A30),"",_xlfn.XLOOKUP(A30,'Requirement Overview'!C:C,'Requirement Overview'!I:I)) -> Inside Sales Executive | G30: =IF(ISBLANK(A30),"",_xlfn.XLOOKUP(A30,'Requirement Overview'!C:C,'Requirement Overview'!G:G)) -> Peritas | H30: Vidhya M Sank | I30: 7 Days | J30: vidyasank2003@gmail.com | K30: 9535796270 | L30: B.E | M30: 6 Months | N30: Simpliaxis Solutions Private Ltd | O30: 2.5 LPA | P30: Bengaluru | Q30: Bengaluru | R30: 3.5 LPA | S30: Screening Reject by Client | T30: Portal-Naukri | U30: 46029 | V30: 46029
A31: D001 | B31: R003 | C31: =IF(ISBLANK(B31),"",_xlfn.XLOOKUP(B31,Recruiter!A:A,Recruiter!B:B)) -> Bhoomika | D31: =IF(ISBLANK(A31),"",_xlfn.XLOOKUP(A31,'Requirement Overview'!C:C,'Requirement Overview'!E:E)) -> Talme | E31: =IF(ISBLANK(A31),"",_xlfn.XLOOKUP(A31,'Requirement Overview'!C:C,'Requirement Overview'!H:H)) -> Non - IT | F31: =IF(ISBLANK(A31),"",_xlfn.XLOOKUP(A31,'Requirement Overview'!C:C,'Requirement Overview'!I:I)) -> Inside Sales Executive | G31: =IF(ISBLANK(A31),"",_xlfn.XLOOKUP(A31,'Requirement Overview'!C:C,'Requirement Overview'!G:G)) -> Peritas | H31: Madiha Yasmeen | I31: Immediately | J31: yasmeenmadiha524@gmail.com | K31: 9880711626 | L31: PUC | M31: 4 Months | N31: Info technology company | O31: 2 LPA | P31: Bengaluru | Q31: Bengaluru | R31: 3.5 LPA | S31: Screening Reject by Client | T31: Portal-Naukri | U31: 46030 | V31: 46030
A32: D001 | B32: R003 | C32: =IF(ISBLANK(B32),"",_xlfn.XLOOKUP(B32,Recruiter!A:A,Recruiter!B:B)) -> Bhoomika | D32: =IF(ISBLANK(A32),"",_xlfn.XLOOKUP(A32,'Requirement Overview'!C:C,'Requirement Overview'!E:E)) -> Talme | E32: =IF(ISBLANK(A32),"",_xlfn.XLOOKUP(A32,'Requirement Overview'!C:C,'Requirement Overview'!H:H)) -> Non - IT | F32: =IF(ISBLANK(A32),"",_xlfn.XLOOKUP(A32,'Requirement Overview'!C:C,'Requirement Overview'!I:I)) -> Inside Sales Executive | G32: =IF(ISBLANK(A32),"",_xlfn.XLOOKUP(A32,'Requirement Overview'!C:C,'Requirement Overview'!G:G)) -> Peritas | H32: Farha Anjum | I32: Immediately | J32: ammuanjum136@gmail.com | K32: 9380875136 | L32: PUC | M32: 4 Years( Telesales) | N32: Blackbuck | O32: 2.5 LPA | P32: Chikkabanavara | Q32: Bengaluru | R32: 3 LPA | S32: Screening Reject by Client | T32: Portal-LinkedIN | U32: 46030 | V32: 46030
A33: D002 | B33: R003 | C33: =IF(ISBLANK(B33),"",_xlfn.XLOOKUP(B33,Recruiter!A:A,Recruiter!B:B)) -> Bhoomika | D33: =IF(ISBLANK(A33),"",_xlfn.XLOOKUP(A33,'Requirement Overview'!C:C,'Requirement Overview'!E:E)) -> Talme | E33: =IF(ISBLANK(A33),"",_xlfn.XLOOKUP(A33,'Requirement Overview'!C:C,'Requirement Overview'!H:H)) -> Non - IT | F33: =IF(ISBLANK(A33),"",_xlfn.XLOOKUP(A33,'Requirement Overview'!C:C,'Requirement Overview'!I:I)) -> Field Sales Executive | G33: =IF(ISBLANK(A33),"",_xlfn.XLOOKUP(A33,'Requirement Overview'!C:C,'Requirement Overview'!G:G)) -> Peritas | H33: Girish | I33: Immediately | J33: girishdivakar04@gmail.com | K33: 9740531518 | L33: B.Com | M33: 2 Years ( Telesales) | N33: Innovative System Pvt Ltd | O33: 2.7 LPA | P33: Bengaluru | Q33: Bengaluru | R33: 3 LPA | S33: Screening Reject by Client | T33: Portal-LinkedIN | U33: 46030 | V33: 46030
A34: D002 | B34: R003 | C34: =IF(ISBLANK(B34),"",_xlfn.XLOOKUP(B34,Recruiter!A:A,Recruiter!B:B)) -> Bhoomika | D34: =IF(ISBLANK(A34),"",_xlfn.XLOOKUP(A34,'Requirement Overview'!C:C,'Requirement Overview'!E:E)) -> Talme | E34: =IF(ISBLANK(A34),"",_xlfn.XLOOKUP(A34,'Requirement Overview'!C:C,'Requirement Overview'!H:H)) -> Non - IT | F34: =IF(ISBLANK(A34),"",_xlfn.XLOOKUP(A34,'Requirement Overview'!C:C,'Requirement Overview'!I:I)) -> Field Sales Executive | G34: =IF(ISBLANK(A34),"",_xlfn.XLOOKUP(A34,'Requirement Overview'!C:C,'Requirement Overview'!G:G)) -> Peritas | H34: Jagannath G | I34: Immediately | J34: mailsforjagan44@gmail.com | K34: 90719 53498 | L34: PUC | M34: 3 Years ( Sales consltunt) | N34: Magic bricks | O34: 3.2 LPA | P34: Bengaluru | Q34: Bengaluru | R34: As per company standards | S34: Screening Reject by Client | T34: Portal-LinkedIN | U34: 46030 | V34: 46030
A35: A003 | B35: R002 | C35: =IF(ISBLANK(B35),"",_xlfn.XLOOKUP(B35,Recruiter!A:A,Recruiter!B:B)) -> Harshitha | D35: =IF(ISBLANK(A35),"",_xlfn.XLOOKUP(A35,'Requirement Overview'!C:C,'Requirement Overview'!E:E)) -> Talme | E35: =IF(ISBLANK(A35),"",_xlfn.XLOOKUP(A35,'Requirement Overview'!C:C,'Requirement Overview'!H:H)) -> IT | F35: =IF(ISBLANK(A35),"",_xlfn.XLOOKUP(A35,'Requirement Overview'!C:C,'Requirement Overview'!I:I)) -> Python Architect | G35: =IF(ISBLANK(A35),"",_xlfn.XLOOKUP(A35,'Requirement Overview'!C:C,'Requirement Overview'!G:G)) -> EMIDS | H35: Sandeep Kumar | I35: Immediately | J35: sandy20mjn@gmail.com | K35: 9456903676 | L35: B.Tech | M35: 14 Years | N35: Bitwise Solutions | O35: 40 LPA | R35: 48 LPA | S35: Screening Reject by Client | T35: Portal-Naukri | U35: 46030 | V35: 46030 | W35: Rejected by panel
A36: A003 | B36: R002 | C36: =IF(ISBLANK(B36),"",_xlfn.XLOOKUP(B36,Recruiter!A:A,Recruiter!B:B)) -> Harshitha | D36: =IF(ISBLANK(A36),"",_xlfn.XLOOKUP(A36,'Requirement Overview'!C:C,'Requirement Overview'!E:E)) -> Talme | E36: =IF(ISBLANK(A36),"",_xlfn.XLOOKUP(A36,'Requirement Overview'!C:C,'Requirement Overview'!H:H)) -> IT | F36: =IF(ISBLANK(A36),"",_xlfn.XLOOKUP(A36,'Requirement Overview'!C:C,'Requirement Overview'!I:I)) -> Python Architect | G36: =IF(ISBLANK(A36),"",_xlfn.XLOOKUP(A36,'Requirement Overview'!C:C,'Requirement Overview'!G:G)) -> EMIDS | H36: rajesh kumar | J36: rajesh7733@gmail.com | K36: 9900297636 | L36: M.Tech | M36: 10 Years | N36: Continental Automotive | O36: 30 LPA | R36: 40 LPA | S36: Screening Reject by Client | T36: Portal-Naukri | U36: 46030 | V36: 46030 | W36: Rejected by panel
A37: A003 | B37: R002 | C37: =IF(ISBLANK(B37),"",_xlfn.XLOOKUP(B37,Recruiter!A:A,Recruiter!B:B)) -> Harshitha | D37: =IF(ISBLANK(A37),"",_xlfn.XLOOKUP(A37,'Requirement Overview'!C:C,'Requirement Overview'!E:E)) -> Talme | E37: =IF(ISBLANK(A37),"",_xlfn.XLOOKUP(A37,'Requirement Overview'!C:C,'Requirement Overview'!H:H)) -> IT | F37: =IF(ISBLANK(A37),"",_xlfn.XLOOKUP(A37,'Requirement Overview'!C:C,'Requirement Overview'!I:I)) -> Python Architect | G37: =IF(ISBLANK(A37),"",_xlfn.XLOOKUP(A37,'Requirement Overview'!C:C,'Requirement Overview'!G:G)) -> EMIDS | H37: JOY MUKHERJEE BHUMANA | J37: joycloud77@gmail.com | K37: 8639873718 | L37: B.Tech | M37: 10.6 Years | N37: GENPACT | O37: 29 LPA | R37: 39 LPA | S37: Tech 1 Reject | T37: Portal-Naukri | U37: 46030 | V37: 46030 | W37: L1 scheduled | X37: 46037 | Y37: Reject
A38: A004 | B38: R002 | C38: =IF(ISBLANK(B38),"",_xlfn.XLOOKUP(B38,Recruiter!A:A,Recruiter!B:B)) -> Harshitha | D38: =IF(ISBLANK(A38),"",_xlfn.XLOOKUP(A38,'Requirement Overview'!C:C,'Requirement Overview'!E:E)) -> Talme | E38: =IF(ISBLANK(A38),"",_xlfn.XLOOKUP(A38,'Requirement Overview'!C:C,'Requirement Overview'!H:H)) -> IT | F38: =IF(ISBLANK(A38),"",_xlfn.XLOOKUP(A38,'Requirement Overview'!C:C,'Requirement Overview'!I:I)) -> Windows system adminstrator | G38: =IF(ISBLANK(A38),"",_xlfn.XLOOKUP(A38,'Requirement Overview'!C:C,'Requirement Overview'!G:G)) -> EMIDS | H38: Rakesh Kumar Mohapatra | J38: aapkarakesh46@gmail.com | K38: 7683937847 | L38: B.Tech | M38: 8 Years | N38: Skylink Communications | O38: 5 LPA | R38: 8 LPA | S38: Screening Reject | T38: Portal-Naukri | U38: 46030 | V38: 46030
A39: A004 | B39: R002 | C39: =IF(ISBLANK(B39),"",_xlfn.XLOOKUP(B39,Recruiter!A:A,Recruiter!B:B)) -> Harshitha | D39: =IF(ISBLANK(A39),"",_xlfn.XLOOKUP(A39,'Requirement Overview'!C:C,'Requirement Overview'!E:E)) -> Talme | E39: =IF(ISBLANK(A39),"",_xlfn.XLOOKUP(A39,'Requirement Overview'!C:C,'Requirement Overview'!H:H)) -> IT | F39: =IF(ISBLANK(A39),"",_xlfn.XLOOKUP(A39,'Requirement Overview'!C:C,'Requirement Overview'!I:I)) -> Windows system adminstrator | G39: =IF(ISBLANK(A39),"",_xlfn.XLOOKUP(A39,'Requirement Overview'!C:C,'Requirement Overview'!G:G)) -> EMIDS | H39: Saikumar | J39: saikumarsingathi31@gmail.com | K39: 9550345310 | L39: B.Tech | M39: 5.5 Years | N39: SMS TECHSOFT INDIA LIMITED | O39: 7.5 LPA | R39: 10 LPA | S39: Tech 1 to be Scheduled | T39: Portal-Naukri | U39: 46030 | V39: 46030
A40: A004 | B40: R002 | C40: =IF(ISBLANK(B40),"",_xlfn.XLOOKUP(B40,Recruiter!A:A,Recruiter!B:B)) -> Harshitha | D40: =IF(ISBLANK(A40),"",_xlfn.XLOOKUP(A40,'Requirement Overview'!C:C,'Requirement Overview'!E:E)) -> Talme | E40: =IF(ISBLANK(A40),"",_xlfn.XLOOKUP(A40,'Requirement Overview'!C:C,'Requirement Overview'!H:H)) -> IT | F40: =IF(ISBLANK(A40),"",_xlfn.XLOOKUP(A40,'Requirement Overview'!C:C,'Requirement Overview'!I:I)) -> Windows system adminstrator | G40: =IF(ISBLANK(A40),"",_xlfn.XLOOKUP(A40,'Requirement Overview'!C:C,'Requirement Overview'!G:G)) -> EMIDS | H40: Pushpendra singh | J40: pushpendrsingh41@gmail.com | K40: 7017152771 | L40: MCA | M40: 6 Years | N40: HCLTech | O40: 5.5 LPA | R40: 8.5 LPA | S40: Screening Reject | T40: Screening Reject | U40: 46030 | V40: 46030
A41: A004 | B41: R002 | C41: =IF(ISBLANK(B41),"",_xlfn.XLOOKUP(B41,Recruiter!A:A,Recruiter!B:B)) -> Harshitha | D41: =IF(ISBLANK(A41),"",_xlfn.XLOOKUP(A41,'Requirement Overview'!C:C,'Requirement Overview'!E:E)) -> Talme | E41: =IF(ISBLANK(A41),"",_xlfn.XLOOKUP(A41,'Requirement Overview'!C:C,'Requirement Overview'!H:H)) -> IT | F41: =IF(ISBLANK(A41),"",_xlfn.XLOOKUP(A41,'Requirement Overview'!C:C,'Requirement Overview'!I:I)) -> Windows system adminstrator | G41: =IF(ISBLANK(A41),"",_xlfn.XLOOKUP(A41,'Requirement Overview'!C:C,'Requirement Overview'!G:G)) -> EMIDS | H41: Raju Gurjar | J41: rajugurjar8072@gmail.com | K41: 9699738072 | L41: B.Tech | M41: 5.5 Years | N41: Quadlabs Technologies | O41: 5.5 LPA | R41: 9 LPA | S41: Screening Reject | T41: Portal-Naukri | U41: 46030 | V41: 46030
A42: A004 | B42: R002 | C42: =IF(ISBLANK(B42),"",_xlfn.XLOOKUP(B42,Recruiter!A:A,Recruiter!B:B)) -> Harshitha | D42: =IF(ISBLANK(A42),"",_xlfn.XLOOKUP(A42,'Requirement Overview'!C:C,'Requirement Overview'!E:E)) -> Talme | E42: =IF(ISBLANK(A42),"",_xlfn.XLOOKUP(A42,'Requirement Overview'!C:C,'Requirement Overview'!H:H)) -> IT | F42: =IF(ISBLANK(A42),"",_xlfn.XLOOKUP(A42,'Requirement Overview'!C:C,'Requirement Overview'!I:I)) -> Windows system adminstrator | G42: =IF(ISBLANK(A42),"",_xlfn.XLOOKUP(A42,'Requirement Overview'!C:C,'Requirement Overview'!G:G)) -> EMIDS | H42: Mohd Abdul Saud | J42: sohailsohail1993@gmail.com | K42: 7799560844 | L42: M.Com | M42: 7 Years | N42: FHPL | O42: 6.2 LPA | R42: 9 LPA | S42: Screening Reject | T42: Portal-Naukri | U42: 46030 | V42: 46030
A43: A004 | B43: R002 | C43: =IF(ISBLANK(B43),"",_xlfn.XLOOKUP(B43,Recruiter!A:A,Recruiter!B:B)) -> Harshitha | D43: =IF(ISBLANK(A43),"",_xlfn.XLOOKUP(A43,'Requirement Overview'!C:C,'Requirement Overview'!E:E)) -> Talme | E43: =IF(ISBLANK(A43),"",_xlfn.XLOOKUP(A43,'Requirement Overview'!C:C,'Requirement Overview'!H:H)) -> IT | F43: =IF(ISBLANK(A43),"",_xlfn.XLOOKUP(A43,'Requirement Overview'!C:C,'Requirement Overview'!I:I)) -> Windows system adminstrator | G43: =IF(ISBLANK(A43),"",_xlfn.XLOOKUP(A43,'Requirement Overview'!C:C,'Requirement Overview'!G:G)) -> EMIDS | H43: Santosh Shanbhag | J43: santoshs23.work@gmail.com | K43: 7975905615 | L43: B.Tech | M43: 5 Years | N43: Deel Payroll India Pvt. Ltd | O43: 8.5 LPA | R43: 10 LPA | S43: Tech 1 Reject | T43: Portal-Naukri | U43: 46029 | V43: 46029 | W43: L1 scheduled | X43: 46037 | Y43: Reject
A44: A004 | B44: R002 | C44: =IF(ISBLANK(B44),"",_xlfn.XLOOKUP(B44,Recruiter!A:A,Recruiter!B:B)) -> Harshitha | D44: =IF(ISBLANK(A44),"",_xlfn.XLOOKUP(A44,'Requirement Overview'!C:C,'Requirement Overview'!E:E)) -> Talme | E44: =IF(ISBLANK(A44),"",_xlfn.XLOOKUP(A44,'Requirement Overview'!C:C,'Requirement Overview'!H:H)) -> IT | F44: =IF(ISBLANK(A44),"",_xlfn.XLOOKUP(A44,'Requirement Overview'!C:C,'Requirement Overview'!I:I)) -> Windows system adminstrator | G44: =IF(ISBLANK(A44),"",_xlfn.XLOOKUP(A44,'Requirement Overview'!C:C,'Requirement Overview'!G:G)) -> EMIDS | H44: Shivaprasad. M | J44: msprasad548@gmail.com | K44: 9381023541 | L44: M.Tech | M44: 6.8 Years | N44: Infosys | O44: 4.86 LPA | R44: 9 LPA | S44: Screening Reject by Client | T44: Portal-Naukri | U44: 46029 | V44: 46029 | W44: Rejected by panel
A45: A004 | B45: R002 | C45: =IF(ISBLANK(B45),"",_xlfn.XLOOKUP(B45,Recruiter!A:A,Recruiter!B:B)) -> Harshitha | D45: =IF(ISBLANK(A45),"",_xlfn.XLOOKUP(A45,'Requirement Overview'!C:C,'Requirement Overview'!E:E)) -> Talme | E45: =IF(ISBLANK(A45),"",_xlfn.XLOOKUP(A45,'Requirement Overview'!C:C,'Requirement Overview'!H:H)) -> IT | F45: =IF(ISBLANK(A45),"",_xlfn.XLOOKUP(A45,'Requirement Overview'!C:C,'Requirement Overview'!I:I)) -> Windows system adminstrator | G45: =IF(ISBLANK(A45),"",_xlfn.XLOOKUP(A45,'Requirement Overview'!C:C,'Requirement Overview'!G:G)) -> EMIDS | H45: MD DANISH HUSSAIN | J45: dinuhussain13@outlook.co | K45: 9546892142 | L45: B.Sc | M45: 5.3 Years | N45: 3i Infotech | O45: 5.5 LPA | R45: 7 LPA | S45: Tech 1 Reject | T45: Portal-Naukri | U45: 46029 | V45: 46029 | W45: L1 scheduled | X45: 46037 | Y45: Reject
A46: A004 | B46: R002 | C46: =IF(ISBLANK(B46),"",_xlfn.XLOOKUP(B46,Recruiter!A:A,Recruiter!B:B)) -> Harshitha | D46: =IF(ISBLANK(A46),"",_xlfn.XLOOKUP(A46,'Requirement Overview'!C:C,'Requirement Overview'!E:E)) -> Talme | E46: =IF(ISBLANK(A46),"",_xlfn.XLOOKUP(A46,'Requirement Overview'!C:C,'Requirement Overview'!H:H)) -> IT | F46: =IF(ISBLANK(A46),"",_xlfn.XLOOKUP(A46,'Requirement Overview'!C:C,'Requirement Overview'!I:I)) -> Windows system adminstrator | G46: =IF(ISBLANK(A46),"",_xlfn.XLOOKUP(A46,'Requirement Overview'!C:C,'Requirement Overview'!G:G)) -> EMIDS | H46: H J Nagesh | J46: nagesh2go@gmail.com | K46: 9008654476 | L46: B.Tech | M46: 6 Years | N46: Toyota Boshoku | O46: 7.97 LPA | R46: 9 LPA | S46: Screening Reject by Client | T46: Portal-Naukri | U46: 46029 | V46: 46029 | W46: Rejected by panel
A47: A004 | B47: R002 | C47: =IF(ISBLANK(B47),"",_xlfn.XLOOKUP(B47,Recruiter!A:A,Recruiter!B:B)) -> Harshitha | D47: =IF(ISBLANK(A47),"",_xlfn.XLOOKUP(A47,'Requirement Overview'!C:C,'Requirement Overview'!E:E)) -> Talme | E47: =IF(ISBLANK(A47),"",_xlfn.XLOOKUP(A47,'Requirement Overview'!C:C,'Requirement Overview'!H:H)) -> IT | F47: =IF(ISBLANK(A47),"",_xlfn.XLOOKUP(A47,'Requirement Overview'!C:C,'Requirement Overview'!I:I)) -> Windows system adminstrator | G47: =IF(ISBLANK(A47),"",_xlfn.XLOOKUP(A47,'Requirement Overview'!C:C,'Requirement Overview'!G:G)) -> EMIDS | H47: Abhinay Singh | J47: kushwah.abhinay@gmail.com | K47: 8445865760 | L47: B.Com | M47: 9 Years | N47: Wipro | O47: 5.5 LPA | R47: 9 LPA ( Offer in hand- 7.5 LPA ) | S47: Screening Reject by Client | T47: Portal-Naukri | U47: 46029 | V47: 46029 | W47: Rejected by panel
A48: A004 | B48: R002 | C48: =IF(ISBLANK(B48),"",_xlfn.XLOOKUP(B48,Recruiter!A:A,Recruiter!B:B)) -> Harshitha | D48: =IF(ISBLANK(A48),"",_xlfn.XLOOKUP(A48,'Requirement Overview'!C:C,'Requirement Overview'!E:E)) -> Talme | E48: =IF(ISBLANK(A48),"",_xlfn.XLOOKUP(A48,'Requirement Overview'!C:C,'Requirement Overview'!H:H)) -> IT | F48: =IF(ISBLANK(A48),"",_xlfn.XLOOKUP(A48,'Requirement Overview'!C:C,'Requirement Overview'!I:I)) -> Windows system adminstrator | G48: =IF(ISBLANK(A48),"",_xlfn.XLOOKUP(A48,'Requirement Overview'!C:C,'Requirement Overview'!G:G)) -> EMIDS | H48: Manikanta Chemaladinne | J48: manikantachemaladinne9@gmail.com | K48: 6362987622 | L48: B.Tech | M48: 5 Years | N48: Wipro | O48: 5 LPA | R48: 8 LPA | S48: Screening Reject by Client | T48: Portal-Naukri | U48: 46029 | V48: 46029 | W48: Rejected by panel
A49: A004 | B49: R002 | C49: =IF(ISBLANK(B49),"",_xlfn.XLOOKUP(B49,Recruiter!A:A,Recruiter!B:B)) -> Harshitha | D49: =IF(ISBLANK(A49),"",_xlfn.XLOOKUP(A49,'Requirement Overview'!C:C,'Requirement Overview'!E:E)) -> Talme | E49: =IF(ISBLANK(A49),"",_xlfn.XLOOKUP(A49,'Requirement Overview'!C:C,'Requirement Overview'!H:H)) -> IT | F49: =IF(ISBLANK(A49),"",_xlfn.XLOOKUP(A49,'Requirement Overview'!C:C,'Requirement Overview'!I:I)) -> Windows system adminstrator | G49: =IF(ISBLANK(A49),"",_xlfn.XLOOKUP(A49,'Requirement Overview'!C:C,'Requirement Overview'!G:G)) -> EMIDS | H49: Shubham Patel | J49: sp.shubham.patel07@gmail.com | K49: 7289872757 | L49: BCA | M49: 5 Years | N49: Progressive Infotech | O49: 7.8 LPA | R49: 9.5 LPA | S49: Screening Reject by Client | T49: Portal-Naukri | U49: 46029 | V49: 46029 | W49: Rejected by panel
A50: A004 | B50: R002 | C50: =IF(ISBLANK(B50),"",_xlfn.XLOOKUP(B50,Recruiter!A:A,Recruiter!B:B)) -> Harshitha | D50: =IF(ISBLANK(A50),"",_xlfn.XLOOKUP(A50,'Requirement Overview'!C:C,'Requirement Overview'!E:E)) -> Talme | E50: =IF(ISBLANK(A50),"",_xlfn.XLOOKUP(A50,'Requirement Overview'!C:C,'Requirement Overview'!H:H)) -> IT | F50: =IF(ISBLANK(A50),"",_xlfn.XLOOKUP(A50,'Requirement Overview'!C:C,'Requirement Overview'!I:I)) -> Windows system adminstrator | G50: =IF(ISBLANK(A50),"",_xlfn.XLOOKUP(A50,'Requirement Overview'!C:C,'Requirement Overview'!G:G)) -> EMIDS | H50: Nitin Gupta | J50: gbeenu@gmail.com | K50: 8586086798 | L50: B.A | M50: 6 Years | N50: Pacific Development | O50: 6 LPA | R50: 9 LPA | S50: Screening Reject by Client | T50: Portal-Naukri | U50: 46029 | V50: 46029 | W50: Rejected by panel
A51: A004 | B51: R002 | C51: =IF(ISBLANK(B51),"",_xlfn.XLOOKUP(B51,Recruiter!A:A,Recruiter!B:B)) -> Harshitha | D51: =IF(ISBLANK(A51),"",_xlfn.XLOOKUP(A51,'Requirement Overview'!C:C,'Requirement Overview'!E:E)) -> Talme | E51: =IF(ISBLANK(A51),"",_xlfn.XLOOKUP(A51,'Requirement Overview'!C:C,'Requirement Overview'!H:H)) -> IT | F51: =IF(ISBLANK(A51),"",_xlfn.XLOOKUP(A51,'Requirement Overview'!C:C,'Requirement Overview'!I:I)) -> Windows system adminstrator | G51: =IF(ISBLANK(A51),"",_xlfn.XLOOKUP(A51,'Requirement Overview'!C:C,'Requirement Overview'!G:G)) -> EMIDS | H51: Ajeet Yadav | J51: yadav.ajeet2872@gmail.com | K51: 9598212872 | L51: MGKVP university | M51: 5 Years | N51: Tech Mahindra | O51: 4.5 LPA | R51: 7 LPA | S51: Screening Reject by Client | T51: Portal-Naukri | U51: 46029 | V51: 46029 | W51: Rejected by panel
A52: A004 | B52: R002 | C52: =IF(ISBLANK(B52),"",_xlfn.XLOOKUP(B52,Recruiter!A:A,Recruiter!B:B)) -> Harshitha | D52: =IF(ISBLANK(A52),"",_xlfn.XLOOKUP(A52,'Requirement Overview'!C:C,'Requirement Overview'!E:E)) -> Talme | E52: =IF(ISBLANK(A52),"",_xlfn.XLOOKUP(A52,'Requirement Overview'!C:C,'Requirement Overview'!H:H)) -> IT | F52: =IF(ISBLANK(A52),"",_xlfn.XLOOKUP(A52,'Requirement Overview'!C:C,'Requirement Overview'!I:I)) -> Windows system adminstrator | G52: =IF(ISBLANK(A52),"",_xlfn.XLOOKUP(A52,'Requirement Overview'!C:C,'Requirement Overview'!G:G)) -> EMIDS | H52: Rasala Chandu Yadav | J52: chandurasala253@gmail.com | K52: 8096286100 | L52: B.Tech | M52: 5.2 Years | N52: IBM | O52: 8 LPA | R52: 10.5 LPA | S52: Tech 1 to be Scheduled | T52: Portal-LinkedIN | U52: 46029 | V52: 46029 | W52: L1 scheduled
A53: A003 | B53: R004 | C53: =IF(ISBLANK(B53),"",_xlfn.XLOOKUP(B53,Recruiter!A:A,Recruiter!B:B)) -> Pooja | D53: =IF(ISBLANK(A53),"",_xlfn.XLOOKUP(A53,'Requirement Overview'!C:C,'Requirement Overview'!E:E)) -> Talme | E53: =IF(ISBLANK(A53),"",_xlfn.XLOOKUP(A53,'Requirement Overview'!C:C,'Requirement Overview'!H:H)) -> IT | F53: =IF(ISBLANK(A53),"",_xlfn.XLOOKUP(A53,'Requirement Overview'!C:C,'Requirement Overview'!I:I)) -> Python Architect | G53: =IF(ISBLANK(A53),"",_xlfn.XLOOKUP(A53,'Requirement Overview'!C:C,'Requirement Overview'!G:G)) -> EMIDS | H53: Abhinav Saxena | J53: abhinavsaxenanit@gmail.com | K53: 7068120242 | L53: M.Tech | M53: 10 Year | N53: iLink Digital | O53: 34 LPA | R53: 50 LPA | S53: Tech 1 Reject | T53: Portal-Naukri | U53: 46031 | V53: 46031 | X53: 46039
A54: A003 | B54: R004 | C54: =IF(ISBLANK(B54),"",_xlfn.XLOOKUP(B54,Recruiter!A:A,Recruiter!B:B)) -> Pooja | D54: =IF(ISBLANK(A54),"",_xlfn.XLOOKUP(A54,'Requirement Overview'!C:C,'Requirement Overview'!E:E)) -> Talme | E54: =IF(ISBLANK(A54),"",_xlfn.XLOOKUP(A54,'Requirement Overview'!C:C,'Requirement Overview'!H:H)) -> IT | F54: =IF(ISBLANK(A54),"",_xlfn.XLOOKUP(A54,'Requirement Overview'!C:C,'Requirement Overview'!I:I)) -> Python Architect | G54: =IF(ISBLANK(A54),"",_xlfn.XLOOKUP(A54,'Requirement Overview'!C:C,'Requirement Overview'!G:G)) -> EMIDS | H54: Kumar Gautam | J54: gautamjamshedpur@gmail.com | K54: 8050641316 | L54: MCA | M54: 15 Year | N54: Harman | O54: 28 LPA | R54: 40 LPA | S54: Tech 1 Reject | T54: Portal-Naukri | U54: 46031 | V54: 46031 | X54: 46041
A55: A003 | B55: R004 | C55: =IF(ISBLANK(B55),"",_xlfn.XLOOKUP(B55,Recruiter!A:A,Recruiter!B:B)) -> Pooja | D55: =IF(ISBLANK(A55),"",_xlfn.XLOOKUP(A55,'Requirement Overview'!C:C,'Requirement Overview'!E:E)) -> Talme | E55: =IF(ISBLANK(A55),"",_xlfn.XLOOKUP(A55,'Requirement Overview'!C:C,'Requirement Overview'!H:H)) -> IT | F55: =IF(ISBLANK(A55),"",_xlfn.XLOOKUP(A55,'Requirement Overview'!C:C,'Requirement Overview'!I:I)) -> Python Architect | G55: =IF(ISBLANK(A55),"",_xlfn.XLOOKUP(A55,'Requirement Overview'!C:C,'Requirement Overview'!G:G)) -> EMIDS | H55: Siva Singh | J55: thakurshiva89@gmail.com | K55: 9045737395 | L55: MCA | M55: 12 Year | N55: Cloud Science Labs | O55: 30 LPA | R55: 35 LPA | S55: Tech 1 Reject | T55: Portal-Naukri | U55: 46031 | V55: 46031 | X55: 46039
A56: A004 | B56: R002 | C56: =IF(ISBLANK(B56),"",_xlfn.XLOOKUP(B56,Recruiter!A:A,Recruiter!B:B)) -> Harshitha | D56: =IF(ISBLANK(A56),"",_xlfn.XLOOKUP(A56,'Requirement Overview'!C:C,'Requirement Overview'!E:E)) -> Talme | E56: =IF(ISBLANK(A56),"",_xlfn.XLOOKUP(A56,'Requirement Overview'!C:C,'Requirement Overview'!H:H)) -> IT | F56: =IF(ISBLANK(A56),"",_xlfn.XLOOKUP(A56,'Requirement Overview'!C:C,'Requirement Overview'!I:I)) -> Windows system adminstrator | G56: =IF(ISBLANK(A56),"",_xlfn.XLOOKUP(A56,'Requirement Overview'!C:C,'Requirement Overview'!G:G)) -> EMIDS | H56: Shubham Sharma | J56: mrshubh04@gmail.com | K56: 8171446365 | L56: MA | M56: 6 Years | N56: 3i Infotech | O56: 5 LPA | R56: 9 LPA | S56: Tech 1 to be Scheduled | T56: Portal-Naukri | U56: 46031 | V56: 46031 | W56: L1 scheduled | X56: 46034
A57: A004 | B57: R002 | C57: =IF(ISBLANK(B57),"",_xlfn.XLOOKUP(B57,Recruiter!A:A,Recruiter!B:B)) -> Harshitha | D57: =IF(ISBLANK(A57),"",_xlfn.XLOOKUP(A57,'Requirement Overview'!C:C,'Requirement Overview'!E:E)) -> Talme | E57: =IF(ISBLANK(A57),"",_xlfn.XLOOKUP(A57,'Requirement Overview'!C:C,'Requirement Overview'!H:H)) -> IT | F57: =IF(ISBLANK(A57),"",_xlfn.XLOOKUP(A57,'Requirement Overview'!C:C,'Requirement Overview'!I:I)) -> Windows system adminstrator | G57: =IF(ISBLANK(A57),"",_xlfn.XLOOKUP(A57,'Requirement Overview'!C:C,'Requirement Overview'!G:G)) -> EMIDS | H57: Mithun Jadhao | J57: mithun.jadhao67@gmail.com | K57: 9607049916 | L57: B.Tech | M57: 5 Years | N57: Quantum link Communication Pvt Ltd | O57: 5 LPA | R57: 7 LPA | S57: Tech 1 to be Scheduled | T57: Portal-Naukri | U57: 46031 | V57: 46031 | W57: L1 scheduled | X57: 46034
A58: A004 | B58: R002 | C58: =IF(ISBLANK(B58),"",_xlfn.XLOOKUP(B58,Recruiter!A:A,Recruiter!B:B)) -> Harshitha | D58: =IF(ISBLANK(A58),"",_xlfn.XLOOKUP(A58,'Requirement Overview'!C:C,'Requirement Overview'!E:E)) -> Talme | E58: =IF(ISBLANK(A58),"",_xlfn.XLOOKUP(A58,'Requirement Overview'!C:C,'Requirement Overview'!H:H)) -> IT | F58: =IF(ISBLANK(A58),"",_xlfn.XLOOKUP(A58,'Requirement Overview'!C:C,'Requirement Overview'!I:I)) -> Windows system adminstrator | G58: =IF(ISBLANK(A58),"",_xlfn.XLOOKUP(A58,'Requirement Overview'!C:C,'Requirement Overview'!G:G)) -> EMIDS | H58: kovuru amreesh kumar | J58: amreeshhardith11@gmail.com | K58: 8121182073 | L58: B.Tech | M58: 5 Years | N58: Genpact | O58: 9 LPA | R58: 10 LPA | S58: Tech 1 to be Scheduled | T58: Portal-Naukri | U58: 46031 | V58: 46031 | W58: L1 scheduled | X58: 46034
A59: C001 | B59: R002 | C59: =IF(ISBLANK(B59),"",_xlfn.XLOOKUP(B59,Recruiter!A:A,Recruiter!B:B)) -> Harshitha | D59: =IF(ISBLANK(A59),"",_xlfn.XLOOKUP(A59,'Requirement Overview'!C:C,'Requirement Overview'!E:E)) -> Talme | E59: =IF(ISBLANK(A59),"",_xlfn.XLOOKUP(A59,'Requirement Overview'!C:C,'Requirement Overview'!H:H)) -> IT | F59: =IF(ISBLANK(A59),"",_xlfn.XLOOKUP(A59,'Requirement Overview'!C:C,'Requirement Overview'!I:I)) -> Data Delivery Manager | G59: =IF(ISBLANK(A59),"",_xlfn.XLOOKUP(A59,'Requirement Overview'!C:C,'Requirement Overview'!G:G)) -> Thoughtfocus | H59: Rakesh Rao MG | J59: rakey0014@gmail.com | K59: 9663289898 | L59: B.E | M59: 14 Years | N59: Chargepoint Technologies | O59: 37 LPA | R59: 45 LPA | S59: Sourced | T59: Portal-Naukri | U59: 46031 | V59: 46031
A60: C001 | B60: R002 | C60: =IF(ISBLANK(B60),"",_xlfn.XLOOKUP(B60,Recruiter!A:A,Recruiter!B:B)) -> Harshitha | D60: =IF(ISBLANK(A60),"",_xlfn.XLOOKUP(A60,'Requirement Overview'!C:C,'Requirement Overview'!E:E)) -> Talme | E60: =IF(ISBLANK(A60),"",_xlfn.XLOOKUP(A60,'Requirement Overview'!C:C,'Requirement Overview'!H:H)) -> IT | F60: =IF(ISBLANK(A60),"",_xlfn.XLOOKUP(A60,'Requirement Overview'!C:C,'Requirement Overview'!I:I)) -> Data Delivery Manager | G60: =IF(ISBLANK(A60),"",_xlfn.XLOOKUP(A60,'Requirement Overview'!C:C,'Requirement Overview'!G:G)) -> Thoughtfocus | H60: Dilip Kumar | J60: dilip.mishra47@yahoo.com | K60: 8010464869 | L60: MCA | M60: 14 Years | N60: Tooliqa | O60: 26 LPA | R60: 36 LPA | S60: Sourced | T60: Portal-Naukri | U60: 46031 | V60: 46031
A61: C001 | B61: R002 | C61: =IF(ISBLANK(B61),"",_xlfn.XLOOKUP(B61,Recruiter!A:A,Recruiter!B:B)) -> Harshitha | D61: =IF(ISBLANK(A61),"",_xlfn.XLOOKUP(A61,'Requirement Overview'!C:C,'Requirement Overview'!E:E)) -> Talme | E61: =IF(ISBLANK(A61),"",_xlfn.XLOOKUP(A61,'Requirement Overview'!C:C,'Requirement Overview'!H:H)) -> IT | F61: =IF(ISBLANK(A61),"",_xlfn.XLOOKUP(A61,'Requirement Overview'!C:C,'Requirement Overview'!I:I)) -> Data Delivery Manager | G61: =IF(ISBLANK(A61),"",_xlfn.XLOOKUP(A61,'Requirement Overview'!C:C,'Requirement Overview'!G:G)) -> Thoughtfocus | H61: shashank | J61: tathagathashashank@gmail.com | K61: 8951736588 | L61: B.E | M61: 10.3 Years | N61: EPAM Systems | O61: 36 LPA | R61: 54 LPA ( Negotiable ) | S61: Sourced | T61: Portal-Naukri | U61: 46031 | V61: 46031
A62: C001 | B62: R002 | C62: =IF(ISBLANK(B62),"",_xlfn.XLOOKUP(B62,Recruiter!A:A,Recruiter!B:B)) -> Harshitha | D62: =IF(ISBLANK(A62),"",_xlfn.XLOOKUP(A62,'Requirement Overview'!C:C,'Requirement Overview'!E:E)) -> Talme | E62: =IF(ISBLANK(A62),"",_xlfn.XLOOKUP(A62,'Requirement Overview'!C:C,'Requirement Overview'!H:H)) -> IT | F62: =IF(ISBLANK(A62),"",_xlfn.XLOOKUP(A62,'Requirement Overview'!C:C,'Requirement Overview'!I:I)) -> Data Delivery Manager | G62: =IF(ISBLANK(A62),"",_xlfn.XLOOKUP(A62,'Requirement Overview'!C:C,'Requirement Overview'!G:G)) -> Thoughtfocus | H62: Nanda Gopal | J62: text2nandha@gmail.com | K62: 8754994013 | L62: BCA | M62: 10.2 Years | N62: Mphasis | O62: 28 LPA | R62: 35 LPA | S62: Sourced | T62: Portal-Naukri | U62: 46031 | V62: 46031
A63: C001 | B63: R002 | C63: =IF(ISBLANK(B63),"",_xlfn.XLOOKUP(B63,Recruiter!A:A,Recruiter!B:B)) -> Harshitha | D63: =IF(ISBLANK(A63),"",_xlfn.XLOOKUP(A63,'Requirement Overview'!C:C,'Requirement Overview'!E:E)) -> Talme | E63: =IF(ISBLANK(A63),"",_xlfn.XLOOKUP(A63,'Requirement Overview'!C:C,'Requirement Overview'!H:H)) -> IT | F63: =IF(ISBLANK(A63),"",_xlfn.XLOOKUP(A63,'Requirement Overview'!C:C,'Requirement Overview'!I:I)) -> Data Delivery Manager | G63: =IF(ISBLANK(A63),"",_xlfn.XLOOKUP(A63,'Requirement Overview'!C:C,'Requirement Overview'!G:G)) -> Thoughtfocus | H63: Prathyusha | J63: rprathyushar@gmail.com | K63: 8939715912 | L63: B.E | M63: 12 Years | N63: Neudesic Technologies | O63: 33 LPA | R63: 40 LPA ( Offer in hand-38 LPA ) | S63: Sourced | T63: Portal-Naukri | U63: 46031 | V63: 46031
A64: E001 | B64: R003 | C64: =IF(ISBLANK(B64),"",_xlfn.XLOOKUP(B64,Recruiter!A:A,Recruiter!B:B)) -> Bhoomika | D64: =IF(ISBLANK(A64),"",_xlfn.XLOOKUP(A64,'Requirement Overview'!C:C,'Requirement Overview'!E:E)) -> Talme | E64: =IF(ISBLANK(A64),"",_xlfn.XLOOKUP(A64,'Requirement Overview'!C:C,'Requirement Overview'!H:H)) -> Non - IT | F64: =IF(ISBLANK(A64),"",_xlfn.XLOOKUP(A64,'Requirement Overview'!C:C,'Requirement Overview'!I:I)) -> Graphic Designer | G64: =IF(ISBLANK(A64),"",_xlfn.XLOOKUP(A64,'Requirement Overview'!C:C,'Requirement Overview'!G:G)) -> Avinashi Ads | H64: PRAKASH | K64: 9025937640 | S64: Screening Reject | T64: Portal-LinkedIN | U64: 46031 | V64: 46031
A65: E001 | B65: R003 | C65: =IF(ISBLANK(B65),"",_xlfn.XLOOKUP(B65,Recruiter!A:A,Recruiter!B:B)) -> Bhoomika | D65: =IF(ISBLANK(A65),"",_xlfn.XLOOKUP(A65,'Requirement Overview'!C:C,'Requirement Overview'!E:E)) -> Talme | E65: =IF(ISBLANK(A65),"",_xlfn.XLOOKUP(A65,'Requirement Overview'!C:C,'Requirement Overview'!H:H)) -> Non - IT | F65: =IF(ISBLANK(A65),"",_xlfn.XLOOKUP(A65,'Requirement Overview'!C:C,'Requirement Overview'!I:I)) -> Graphic Designer | G65: =IF(ISBLANK(A65),"",_xlfn.XLOOKUP(A65,'Requirement Overview'!C:C,'Requirement Overview'!G:G)) -> Avinashi Ads | H65: Arjun Kumar | K65: 9716790203 | S65: Screening Reject | T65: Portal-LinkedIN | U65: 46031 | V65: 46031
A66: E001 | B66: R003 | C66: =IF(ISBLANK(B66),"",_xlfn.XLOOKUP(B66,Recruiter!A:A,Recruiter!B:B)) -> Bhoomika | D66: =IF(ISBLANK(A66),"",_xlfn.XLOOKUP(A66,'Requirement Overview'!C:C,'Requirement Overview'!E:E)) -> Talme | E66: =IF(ISBLANK(A66),"",_xlfn.XLOOKUP(A66,'Requirement Overview'!C:C,'Requirement Overview'!H:H)) -> Non - IT | F66: =IF(ISBLANK(A66),"",_xlfn.XLOOKUP(A66,'Requirement Overview'!C:C,'Requirement Overview'!I:I)) -> Graphic Designer | G66: =IF(ISBLANK(A66),"",_xlfn.XLOOKUP(A66,'Requirement Overview'!C:C,'Requirement Overview'!G:G)) -> Avinashi Ads | H66: Saikiran Jennay | K66: 6300030330 | S66: Screening Reject | T66: Portal-LinkedIN | U66: 46031 | V66: 46031
A67: E001 | B67: R003 | C67: =IF(ISBLANK(B67),"",_xlfn.XLOOKUP(B67,Recruiter!A:A,Recruiter!B:B)) -> Bhoomika | D67: =IF(ISBLANK(A67),"",_xlfn.XLOOKUP(A67,'Requirement Overview'!C:C,'Requirement Overview'!E:E)) -> Talme | E67: =IF(ISBLANK(A67),"",_xlfn.XLOOKUP(A67,'Requirement Overview'!C:C,'Requirement Overview'!H:H)) -> Non - IT | F67: =IF(ISBLANK(A67),"",_xlfn.XLOOKUP(A67,'Requirement Overview'!C:C,'Requirement Overview'!I:I)) -> Graphic Designer | G67: =IF(ISBLANK(A67),"",_xlfn.XLOOKUP(A67,'Requirement Overview'!C:C,'Requirement Overview'!G:G)) -> Avinashi Ads | H67: VINAYAK ACHARYA | K67: 6363447926 | S67: Screening Reject | T67: Portal-LinkedIN | U67: 46031 | V67: 46031
A68: E001 | B68: R003 | C68: =IF(ISBLANK(B68),"",_xlfn.XLOOKUP(B68,Recruiter!A:A,Recruiter!B:B)) -> Bhoomika | D68: =IF(ISBLANK(A68),"",_xlfn.XLOOKUP(A68,'Requirement Overview'!C:C,'Requirement Overview'!E:E)) -> Talme | E68: =IF(ISBLANK(A68),"",_xlfn.XLOOKUP(A68,'Requirement Overview'!C:C,'Requirement Overview'!H:H)) -> Non - IT | F68: =IF(ISBLANK(A68),"",_xlfn.XLOOKUP(A68,'Requirement Overview'!C:C,'Requirement Overview'!I:I)) -> Graphic Designer | G68: =IF(ISBLANK(A68),"",_xlfn.XLOOKUP(A68,'Requirement Overview'!C:C,'Requirement Overview'!G:G)) -> Avinashi Ads | H68: ZABIULLA | K68: 6303733025 | S68: Screening Reject | T68: Portal-LinkedIN | U68: 46031 | V68: 46031
A69: E001 | B69: R003 | C69: =IF(ISBLANK(B69),"",_xlfn.XLOOKUP(B69,Recruiter!A:A,Recruiter!B:B)) -> Bhoomika | D69: =IF(ISBLANK(A69),"",_xlfn.XLOOKUP(A69,'Requirement Overview'!C:C,'Requirement Overview'!E:E)) -> Talme | E69: =IF(ISBLANK(A69),"",_xlfn.XLOOKUP(A69,'Requirement Overview'!C:C,'Requirement Overview'!H:H)) -> Non - IT | F69: =IF(ISBLANK(A69),"",_xlfn.XLOOKUP(A69,'Requirement Overview'!C:C,'Requirement Overview'!I:I)) -> Graphic Designer | G69: =IF(ISBLANK(A69),"",_xlfn.XLOOKUP(A69,'Requirement Overview'!C:C,'Requirement Overview'!G:G)) -> Avinashi Ads | H69: MAHESH HM | I69: 15 Days | J69: mahimaheshhm2001@gmail.com | K69: 9972367632 | L69: B.E | M69: 1 Year | N69: Sahara Group of Industries | O69: 2.7 lpa | P69: Bengaluru | Q69: Bengaluru | R69: 3.7 lpa | S69: Screening Reject by Client | T69: Portal-LinkedIN | U69: 46031 | V69: 46031
A70: E001 | B70: R003 | C70: =IF(ISBLANK(B70),"",_xlfn.XLOOKUP(B70,Recruiter!A:A,Recruiter!B:B)) -> Bhoomika | D70: =IF(ISBLANK(A70),"",_xlfn.XLOOKUP(A70,'Requirement Overview'!C:C,'Requirement Overview'!E:E)) -> Talme | E70: =IF(ISBLANK(A70),"",_xlfn.XLOOKUP(A70,'Requirement Overview'!C:C,'Requirement Overview'!H:H)) -> Non - IT | F70: =IF(ISBLANK(A70),"",_xlfn.XLOOKUP(A70,'Requirement Overview'!C:C,'Requirement Overview'!I:I)) -> Graphic Designer | G70: =IF(ISBLANK(A70),"",_xlfn.XLOOKUP(A70,'Requirement Overview'!C:C,'Requirement Overview'!G:G)) -> Avinashi Ads | H70: CHINTHATEJASWINI | I70: 30 Days | J70: tejuchintha99@gmail.com | K70: 6363447926 | L70: BSC | M70: 1.6 Year | N70: Iyla Silk Pvt Ltd | O70: 2.8 lpa | P70: Bengaluru | Q70: Bengaluru | R70: 3.5 lpa | S70: Screening Reject by Client | T70: Portal-LinkedIN | U70: 46031 | V70: 46031
A71: D001 | B71: R004 | C71: Pooja | D71: Talme | E71: Non - IT | F71: Inside Sales | G71: Peritas | H71: Manjunath K | J71: km.manjunath.krishna21@gmail.com | K71: 6363651396 | L71: B.Com | M71: 3 Year | N71: Varsha Enterprises | O71: 14.5 K | R71: As per company standard | S71: Screening reject by HR | T71: Immediate | U71: 46031 | V71: 46031
A72: A004 | B72: R005 | C72: =IF(ISBLANK(B72),"",_xlfn.XLOOKUP(B72,Recruiter!A:A,Recruiter!B:B)) -> Narthana | D72: =IF(ISBLANK(A72),"",_xlfn.XLOOKUP(A72,'Requirement Overview'!C:C,'Requirement Overview'!E:E)) -> Talme | E72: =IF(ISBLANK(A72),"",_xlfn.XLOOKUP(A72,'Requirement Overview'!C:C,'Requirement Overview'!H:H)) -> IT | F72: =IF(ISBLANK(A72),"",_xlfn.XLOOKUP(A72,'Requirement Overview'!C:C,'Requirement Overview'!I:I)) -> Windows system adminstrator | G72: =IF(ISBLANK(A72),"",_xlfn.XLOOKUP(A72,'Requirement Overview'!C:C,'Requirement Overview'!G:G)) -> EMIDS | H72: Sreenivasulu | I72: Immediate Joiner LWD 5 Dec 2025 | J72: sreenivasduvvuru15@gmail.com | K72: 9490296380 | M72: 6.4 Years | N72: UST Global | O72: 6 LPA | R72: 10.5 LPA | S72: Sourced | T72: Portal-Naukri | U72: 46031 | V72: 46031
A73: A004 | B73: R005 | C73: =IF(ISBLANK(B73),"",_xlfn.XLOOKUP(B73,Recruiter!A:A,Recruiter!B:B)) -> Narthana | D73: =IF(ISBLANK(A73),"",_xlfn.XLOOKUP(A73,'Requirement Overview'!C:C,'Requirement Overview'!E:E)) -> Talme | E73: =IF(ISBLANK(A73),"",_xlfn.XLOOKUP(A73,'Requirement Overview'!C:C,'Requirement Overview'!H:H)) -> IT | F73: =IF(ISBLANK(A73),"",_xlfn.XLOOKUP(A73,'Requirement Overview'!C:C,'Requirement Overview'!I:I)) -> Windows system adminstrator | G73: =IF(ISBLANK(A73),"",_xlfn.XLOOKUP(A73,'Requirement Overview'!C:C,'Requirement Overview'!G:G)) -> EMIDS | H73: Balamuraga | I73: Immediate Joiner LWD 3 Oct 2025 | J73: balamuragak05@gmail.com | K73: 8688773988 | M73: 5 Years | N73: Kripya solutions private limited | O73: 7 LPA | R73: 10.5 LPA | S73: Sourced | T73: Portal-Naukri | U73: 46031 | V73: 46031
A74: A004 | B74: R005 | C74: =IF(ISBLANK(B74),"",_xlfn.XLOOKUP(B74,Recruiter!A:A,Recruiter!B:B)) -> Narthana | D74: =IF(ISBLANK(A74),"",_xlfn.XLOOKUP(A74,'Requirement Overview'!C:C,'Requirement Overview'!E:E)) -> Talme | E74: =IF(ISBLANK(A74),"",_xlfn.XLOOKUP(A74,'Requirement Overview'!C:C,'Requirement Overview'!H:H)) -> IT | F74: =IF(ISBLANK(A74),"",_xlfn.XLOOKUP(A74,'Requirement Overview'!C:C,'Requirement Overview'!I:I)) -> Windows system adminstrator | G74: =IF(ISBLANK(A74),"",_xlfn.XLOOKUP(A74,'Requirement Overview'!C:C,'Requirement Overview'!G:G)) -> EMIDS | H74: Naresh Bodapatla | I74: Immediate Joiner LWD july 2024 | J74: nareshbodapatla18@gmail.com | K74: 9866264265 | M74: 6.6 Years | N74: Trianz Consulting pvt | O74: 5.3 LPA | R74: 8 LPA | S74: Sourced | T74: Portal-Naukri | U74: 46031 | V74: 46031
A75: B001 | B75: R005 | C75: =IF(ISBLANK(B75),"",_xlfn.XLOOKUP(B75,Recruiter!A:A,Recruiter!B:B)) -> Narthana | D75: =IF(ISBLANK(A75),"",_xlfn.XLOOKUP(A75,'Requirement Overview'!C:C,'Requirement Overview'!E:E)) -> Talme | E75: =IF(ISBLANK(A75),"",_xlfn.XLOOKUP(A75,'Requirement Overview'!C:C,'Requirement Overview'!H:H)) -> IT | F75: =IF(ISBLANK(A75),"",_xlfn.XLOOKUP(A75,'Requirement Overview'!C:C,'Requirement Overview'!I:I)) -> Android BSP Developer | G75: =IF(ISBLANK(A75),"",_xlfn.XLOOKUP(A75,'Requirement Overview'!C:C,'Requirement Overview'!G:G)) -> KPIT | H75: Aswini | I75: 90 Days Neg(30 days) | J75: ashwinimallanagowda@gmail.com | K75: 9739951590 | M75: 8 Years | N75: L&T Technology Services | O75: 12 LPA | R75: 22 LPA | S75: Yet to Screen | T75: Portal-Naukri | U75: 46030 | V75: 46030
A76: B001 | B76: R005 | C76: =IF(ISBLANK(B76),"",_xlfn.XLOOKUP(B76,Recruiter!A:A,Recruiter!B:B)) -> Narthana | D76: =IF(ISBLANK(A76),"",_xlfn.XLOOKUP(A76,'Requirement Overview'!C:C,'Requirement Overview'!E:E)) -> Talme | E76: =IF(ISBLANK(A76),"",_xlfn.XLOOKUP(A76,'Requirement Overview'!C:C,'Requirement Overview'!H:H)) -> IT | F76: =IF(ISBLANK(A76),"",_xlfn.XLOOKUP(A76,'Requirement Overview'!C:C,'Requirement Overview'!I:I)) -> Android BSP Developer | G76: =IF(ISBLANK(A76),"",_xlfn.XLOOKUP(A76,'Requirement Overview'!C:C,'Requirement Overview'!G:G)) -> KPIT | H76: Tanmay Desai | I76: 60 Days Neg(45 days) | J76: tndesai25@gmail.com | K76: 7567041466 | M76: 11.5 Years | N76: Tata Elxsi Pvt Ltd, | O76: 20 LPA | R76: 29 LPA | S76: Yet to Screen | T76: Portal-Naukri | U76: 46030 | V76: 46030
A77: B001 | B77: R005 | C77: =IF(ISBLANK(B77),"",_xlfn.XLOOKUP(B77,Recruiter!A:A,Recruiter!B:B)) -> Narthana | D77: =IF(ISBLANK(A77),"",_xlfn.XLOOKUP(A77,'Requirement Overview'!C:C,'Requirement Overview'!E:E)) -> Talme | E77: =IF(ISBLANK(A77),"",_xlfn.XLOOKUP(A77,'Requirement Overview'!C:C,'Requirement Overview'!H:H)) -> IT | F77: =IF(ISBLANK(A77),"",_xlfn.XLOOKUP(A77,'Requirement Overview'!C:C,'Requirement Overview'!I:I)) -> Android BSP Developer | G77: =IF(ISBLANK(A77),"",_xlfn.XLOOKUP(A77,'Requirement Overview'!C:C,'Requirement Overview'!G:G)) -> KPIT | H77: SatyaNarayan | I77: 30 Days Neg(15 Days) | J77: narayansatyajr6@gmail.com | K77: 9380151120 | M77: 9 Years | N77: Collaborate Solutions( | O77: 21 LPA | R77: 27 LPA | S77: Yet to Screen | T77: Portal-Naukri | U77: 46030 | V77: 46030
A78: B001 | B78: R005 | C78: =IF(ISBLANK(B78),"",_xlfn.XLOOKUP(B78,Recruiter!A:A,Recruiter!B:B)) -> Narthana | D78: =IF(ISBLANK(A78),"",_xlfn.XLOOKUP(A78,'Requirement Overview'!C:C,'Requirement Overview'!E:E)) -> Talme | E78: =IF(ISBLANK(A78),"",_xlfn.XLOOKUP(A78,'Requirement Overview'!C:C,'Requirement Overview'!H:H)) -> IT | F78: =IF(ISBLANK(A78),"",_xlfn.XLOOKUP(A78,'Requirement Overview'!C:C,'Requirement Overview'!I:I)) -> Android BSP Developer | G78: =IF(ISBLANK(A78),"",_xlfn.XLOOKUP(A78,'Requirement Overview'!C:C,'Requirement Overview'!G:G)) -> KPIT | H78: Subham Dey | I78: LWD 06 Feb 2026 | J78: subhamdeyece@gmail.com | K78: 8197684687 | M78: 7.5 Years | N78: Bosch Global Software Technologies | O78: 14.5 LPA | R78: 20 LPA | S78: Yet to Screen | T78: Portal-Naukri | U78: 46030 | V78: 46030
A79: H003 | B79: R003 | C79: =IF(ISBLANK(B79),"",_xlfn.XLOOKUP(B79,Recruiter!A:A,Recruiter!B:B)) -> Bhoomika | D79: =IF(ISBLANK(A79),"",_xlfn.XLOOKUP(A79,'Requirement Overview'!C:C,'Requirement Overview'!E:E)) -> Talme | E79: =IF(ISBLANK(A79),"",_xlfn.XLOOKUP(A79,'Requirement Overview'!C:C,'Requirement Overview'!H:H)) -> IT | F79: =IF(ISBLANK(A79),"",_xlfn.XLOOKUP(A79,'Requirement Overview'!C:C,'Requirement Overview'!I:I)) -> HR Recruiter | G79: =IF(ISBLANK(A79),"",_xlfn.XLOOKUP(A79,'Requirement Overview'!C:C,'Requirement Overview'!G:G)) -> Talme | H79: Priya Ghosh | K79: 8370889483 | S79: Screening Reject by Client | T79: Portal-LinkedIN | U79: 46034 | V79: 46034
A80: H003 | B80: R003 | C80: =IF(ISBLANK(B80),"",_xlfn.XLOOKUP(B80,Recruiter!A:A,Recruiter!B:B)) -> Bhoomika | D80: =IF(ISBLANK(A80),"",_xlfn.XLOOKUP(A80,'Requirement Overview'!C:C,'Requirement Overview'!E:E)) -> Talme | E80: =IF(ISBLANK(A80),"",_xlfn.XLOOKUP(A80,'Requirement Overview'!C:C,'Requirement Overview'!H:H)) -> IT | F80: =IF(ISBLANK(A80),"",_xlfn.XLOOKUP(A80,'Requirement Overview'!C:C,'Requirement Overview'!I:I)) -> HR Recruiter | G80: =IF(ISBLANK(A80),"",_xlfn.XLOOKUP(A80,'Requirement Overview'!C:C,'Requirement Overview'!G:G)) -> Talme | H80: yamini | K80: 8904518053 | S80: Screening Reject by Client | T80: Portal-LinkedIN | U80: 46034 | V80: 46034
A81: H003 | B81: R003 | C81: =IF(ISBLANK(B81),"",_xlfn.XLOOKUP(B81,Recruiter!A:A,Recruiter!B:B)) -> Bhoomika | D81: =IF(ISBLANK(A81),"",_xlfn.XLOOKUP(A81,'Requirement Overview'!C:C,'Requirement Overview'!E:E)) -> Talme | E81: =IF(ISBLANK(A81),"",_xlfn.XLOOKUP(A81,'Requirement Overview'!C:C,'Requirement Overview'!H:H)) -> IT | F81: =IF(ISBLANK(A81),"",_xlfn.XLOOKUP(A81,'Requirement Overview'!C:C,'Requirement Overview'!I:I)) -> HR Recruiter | G81: =IF(ISBLANK(A81),"",_xlfn.XLOOKUP(A81,'Requirement Overview'!C:C,'Requirement Overview'!G:G)) -> Talme | H81: ASTHA PORWAL | K81: 8305457822 | S81: Screening Reject by Client | T81: Portal-LinkedIN | U81: 46034 | V81: 46034
A82: H003 | B82: R003 | C82: =IF(ISBLANK(B82),"",_xlfn.XLOOKUP(B82,Recruiter!A:A,Recruiter!B:B)) -> Bhoomika | D82: =IF(ISBLANK(A82),"",_xlfn.XLOOKUP(A82,'Requirement Overview'!C:C,'Requirement Overview'!E:E)) -> Talme | E82: =IF(ISBLANK(A82),"",_xlfn.XLOOKUP(A82,'Requirement Overview'!C:C,'Requirement Overview'!H:H)) -> IT | F82: =IF(ISBLANK(A82),"",_xlfn.XLOOKUP(A82,'Requirement Overview'!C:C,'Requirement Overview'!I:I)) -> HR Recruiter | G82: =IF(ISBLANK(A82),"",_xlfn.XLOOKUP(A82,'Requirement Overview'!C:C,'Requirement Overview'!G:G)) -> Talme | H82: Neha Thomas | I82: Immediately | J82: nehart2002@gmail.com | K82: 8590086590 | L82: MBA | M82: 1 Years | N82: Redaptive Services Pvt Ltd | O82: 2.4 LPA | P82: Pune | Q82: Bengaluru | R82: As per company standard | S82: Screening Reject by Client | T82: Portal-LinkedIN | U82: 46034 | V82: 46034
A83: H003 | B83: R003 | C83: =IF(ISBLANK(B83),"",_xlfn.XLOOKUP(B83,Recruiter!A:A,Recruiter!B:B)) -> Bhoomika | D83: =IF(ISBLANK(A83),"",_xlfn.XLOOKUP(A83,'Requirement Overview'!C:C,'Requirement Overview'!E:E)) -> Talme | E83: =IF(ISBLANK(A83),"",_xlfn.XLOOKUP(A83,'Requirement Overview'!C:C,'Requirement Overview'!H:H)) -> IT | F83: =IF(ISBLANK(A83),"",_xlfn.XLOOKUP(A83,'Requirement Overview'!C:C,'Requirement Overview'!I:I)) -> HR Recruiter | G83: =IF(ISBLANK(A83),"",_xlfn.XLOOKUP(A83,'Requirement Overview'!C:C,'Requirement Overview'!G:G)) -> Talme | H83: rithesh | I83: Immediately | J83: rritheshpoojary7@gmail.com | K83: 9663650280 | L83: MSW | M83: Fresher | N83: NIL | O83: NIL | P83: Bengaluru | Q83: Bengaluru | R83: As per company standard | S83: Screening reject by HR | T83: Portal-LinkedIN | U83: 46034 | V83: 46034
A84: H003 | B84: R003 | C84: =IF(ISBLANK(B84),"",_xlfn.XLOOKUP(B84,Recruiter!A:A,Recruiter!B:B)) -> Bhoomika | D84: =IF(ISBLANK(A84),"",_xlfn.XLOOKUP(A84,'Requirement Overview'!C:C,'Requirement Overview'!E:E)) -> Talme | E84: =IF(ISBLANK(A84),"",_xlfn.XLOOKUP(A84,'Requirement Overview'!C:C,'Requirement Overview'!H:H)) -> IT | F84: =IF(ISBLANK(A84),"",_xlfn.XLOOKUP(A84,'Requirement Overview'!C:C,'Requirement Overview'!I:I)) -> HR Recruiter | G84: =IF(ISBLANK(A84),"",_xlfn.XLOOKUP(A84,'Requirement Overview'!C:C,'Requirement Overview'!G:G)) -> Talme | H84: MOHAMED MUSTHAFA H.R | K84: 8248991226 | S84: Screening Reject | T84: Portal-LinkedIN | U84: 46034 | V84: 46034
A85: H003 | B85: R003 | C85: =IF(ISBLANK(B85),"",_xlfn.XLOOKUP(B85,Recruiter!A:A,Recruiter!B:B)) -> Bhoomika | D85: =IF(ISBLANK(A85),"",_xlfn.XLOOKUP(A85,'Requirement Overview'!C:C,'Requirement Overview'!E:E)) -> Talme | E85: =IF(ISBLANK(A85),"",_xlfn.XLOOKUP(A85,'Requirement Overview'!C:C,'Requirement Overview'!H:H)) -> IT | F85: =IF(ISBLANK(A85),"",_xlfn.XLOOKUP(A85,'Requirement Overview'!C:C,'Requirement Overview'!I:I)) -> HR Recruiter | G85: =IF(ISBLANK(A85),"",_xlfn.XLOOKUP(A85,'Requirement Overview'!C:C,'Requirement Overview'!G:G)) -> Talme | H85: Narra Hemalatha | K85: 9347957046 | S85: Screening Reject | T85: Portal-LinkedIN | U85: 46034 | V85: 46034
A86: H003 | B86: R003 | C86: =IF(ISBLANK(B86),"",_xlfn.XLOOKUP(B86,Recruiter!A:A,Recruiter!B:B)) -> Bhoomika | D86: =IF(ISBLANK(A86),"",_xlfn.XLOOKUP(A86,'Requirement Overview'!C:C,'Requirement Overview'!E:E)) -> Talme | E86: =IF(ISBLANK(A86),"",_xlfn.XLOOKUP(A86,'Requirement Overview'!C:C,'Requirement Overview'!H:H)) -> IT | F86: =IF(ISBLANK(A86),"",_xlfn.XLOOKUP(A86,'Requirement Overview'!C:C,'Requirement Overview'!I:I)) -> HR Recruiter | G86: =IF(ISBLANK(A86),"",_xlfn.XLOOKUP(A86,'Requirement Overview'!C:C,'Requirement Overview'!G:G)) -> Talme | H86: KEERTHIKA. P | K86: 9344204373 | S86: Screening Reject | T86: Portal-LinkedIN | U86: 46034 | V86: 46034
A87: H003 | B87: R003 | C87: =IF(ISBLANK(B87),"",_xlfn.XLOOKUP(B87,Recruiter!A:A,Recruiter!B:B)) -> Bhoomika | D87: =IF(ISBLANK(A87),"",_xlfn.XLOOKUP(A87,'Requirement Overview'!C:C,'Requirement Overview'!E:E)) -> Talme | E87: =IF(ISBLANK(A87),"",_xlfn.XLOOKUP(A87,'Requirement Overview'!C:C,'Requirement Overview'!H:H)) -> IT | F87: =IF(ISBLANK(A87),"",_xlfn.XLOOKUP(A87,'Requirement Overview'!C:C,'Requirement Overview'!I:I)) -> HR Recruiter | G87: =IF(ISBLANK(A87),"",_xlfn.XLOOKUP(A87,'Requirement Overview'!C:C,'Requirement Overview'!G:G)) -> Talme | H87: akshay | I87: Immediately | J87: kshaydevale123@gmail.com | K87: 7022661140 | L87: MBA | M87: Fresher | N87: NIL | O87: NIL | P87: Bengaluru | Q87: Bengaluru | R87: As per company standard | S87: Screening Reject by Client | T87: Portal-LinkedIN | U87: 46034 | V87: 46034
A88: H003 | B88: R003 | C88: =IF(ISBLANK(B88),"",_xlfn.XLOOKUP(B88,Recruiter!A:A,Recruiter!B:B)) -> Bhoomika | D88: =IF(ISBLANK(A88),"",_xlfn.XLOOKUP(A88,'Requirement Overview'!C:C,'Requirement Overview'!E:E)) -> Talme | E88: =IF(ISBLANK(A88),"",_xlfn.XLOOKUP(A88,'Requirement Overview'!C:C,'Requirement Overview'!H:H)) -> IT | F88: =IF(ISBLANK(A88),"",_xlfn.XLOOKUP(A88,'Requirement Overview'!C:C,'Requirement Overview'!I:I)) -> HR Recruiter | G88: =IF(ISBLANK(A88),"",_xlfn.XLOOKUP(A88,'Requirement Overview'!C:C,'Requirement Overview'!G:G)) -> Talme | H88: Sakshi Saini | I88: Immediately | J88: sainisakshi183@gmail.com | K88: 7488168092 | L88: Diploman | M88: Fresher | N88: NIL | O88: NIL | P88: Bengaluru | Q88: Bengaluru | R88: As per company standard | S88: Screening Reject by Client | T88: Portal-LinkedIN | U88: 46034 | V88: 46034
A89: H003 | B89: R003 | C89: =IF(ISBLANK(B89),"",_xlfn.XLOOKUP(B89,Recruiter!A:A,Recruiter!B:B)) -> Bhoomika | D89: =IF(ISBLANK(A89),"",_xlfn.XLOOKUP(A89,'Requirement Overview'!C:C,'Requirement Overview'!E:E)) -> Talme | E89: =IF(ISBLANK(A89),"",_xlfn.XLOOKUP(A89,'Requirement Overview'!C:C,'Requirement Overview'!H:H)) -> IT | F89: =IF(ISBLANK(A89),"",_xlfn.XLOOKUP(A89,'Requirement Overview'!C:C,'Requirement Overview'!I:I)) -> HR Recruiter | G89: =IF(ISBLANK(A89),"",_xlfn.XLOOKUP(A89,'Requirement Overview'!C:C,'Requirement Overview'!G:G)) -> Talme | H89: chandana | I89: Immediately | J89: chandanababu2003@gmail.com | K89: 8088808200 | L89: MBA | M89: Fresher | N89: NIL | O89: NIL | P89: Bengaluru | Q89: Bengaluru | R89: As per company standard | S89: Screening Reject by Client | T89: Portal-LinkedIN | U89: 46034 | V89: 46034
A90: E005 | B90: R004 | C90: =IF(ISBLANK(B90),"",_xlfn.XLOOKUP(B90,Recruiter!A:A,Recruiter!B:B)) -> Pooja | D90: =IF(ISBLANK(A90),"",_xlfn.XLOOKUP(A90,'Requirement Overview'!C:C,'Requirement Overview'!E:E)) -> Talme | E90: =IF(ISBLANK(A90),"",_xlfn.XLOOKUP(A90,'Requirement Overview'!C:C,'Requirement Overview'!H:H)) -> Non - IT | F90: =IF(ISBLANK(A90),"",_xlfn.XLOOKUP(A90,'Requirement Overview'!C:C,'Requirement Overview'!I:I)) -> Key Accounts Manager | G90: =IF(ISBLANK(A90),"",_xlfn.XLOOKUP(A90,'Requirement Overview'!C:C,'Requirement Overview'!G:G)) -> Avinashi Ads | H90: Aaqib Subhani Askari | I90: Immediate | J90: aaqib.subhani1031@gmail.com | K90: 9611277031 | L90: MBA | M90: 6.10 Year | N90: TOKYO AnalyticX | O90: 11 LPA | R90: Same or above | S90: Screening Reject by Client | T90: Portal-Naukri | U90: 46034 | V90: 46034
A91: E005 | B91: R004 | C91: =IF(ISBLANK(B91),"",_xlfn.XLOOKUP(B91,Recruiter!A:A,Recruiter!B:B)) -> Pooja | D91: =IF(ISBLANK(A91),"",_xlfn.XLOOKUP(A91,'Requirement Overview'!C:C,'Requirement Overview'!E:E)) -> Talme | E91: =IF(ISBLANK(A91),"",_xlfn.XLOOKUP(A91,'Requirement Overview'!C:C,'Requirement Overview'!H:H)) -> Non - IT | F91: =IF(ISBLANK(A91),"",_xlfn.XLOOKUP(A91,'Requirement Overview'!C:C,'Requirement Overview'!I:I)) -> Key Accounts Manager | G91: =IF(ISBLANK(A91),"",_xlfn.XLOOKUP(A91,'Requirement Overview'!C:C,'Requirement Overview'!G:G)) -> Avinashi Ads | H91: Zeeshan | I91: Immediate | J91: zeeshanm851@gmail.com | K91: 9686908119 | L91: MBA | M91: 6.6 Year | N91: Elite Elevators | O91: 9 LPA | R91: 30% Hike | S91: Screening Reject by Client | T91: Portal-Naukri | U91: 46034 | V91: 46034
A92: E005 | B92: R004 | C92: =IF(ISBLANK(B92),"",_xlfn.XLOOKUP(B92,Recruiter!A:A,Recruiter!B:B)) -> Pooja | D92: =IF(ISBLANK(A92),"",_xlfn.XLOOKUP(A92,'Requirement Overview'!C:C,'Requirement Overview'!E:E)) -> Talme | E92: =IF(ISBLANK(A92),"",_xlfn.XLOOKUP(A92,'Requirement Overview'!C:C,'Requirement Overview'!H:H)) -> Non - IT | F92: =IF(ISBLANK(A92),"",_xlfn.XLOOKUP(A92,'Requirement Overview'!C:C,'Requirement Overview'!I:I)) -> Key Accounts Manager | G92: =IF(ISBLANK(A92),"",_xlfn.XLOOKUP(A92,'Requirement Overview'!C:C,'Requirement Overview'!G:G)) -> Avinashi Ads | H92: Manoranjith D N | I92: 15 Days | J92: manu.dn03@gmail.com | K92: 9902295595 | L92: BE | M92: 8 Year | N92: Torry Harris Integration solutions | O92: 12 LPA | R92: 16.5 LPA | S92: Awaiting feedback from client | T92: Portal-Naukri | U92: 46034 | V92: 46034
A93: E004 | B93: R004 | C93: =IF(ISBLANK(B93),"",_xlfn.XLOOKUP(B93,Recruiter!A:A,Recruiter!B:B)) -> Pooja | D93: =IF(ISBLANK(A93),"",_xlfn.XLOOKUP(A93,'Requirement Overview'!C:C,'Requirement Overview'!E:E)) -> Talme | E93: =IF(ISBLANK(A93),"",_xlfn.XLOOKUP(A93,'Requirement Overview'!C:C,'Requirement Overview'!H:H)) -> Non - IT | F93: =IF(ISBLANK(A93),"",_xlfn.XLOOKUP(A93,'Requirement Overview'!C:C,'Requirement Overview'!I:I)) -> Associate Sales | G93: =IF(ISBLANK(A93),"",_xlfn.XLOOKUP(A93,'Requirement Overview'!C:C,'Requirement Overview'!G:G)) -> Avinashi Ads | H93: CHANDANA G S | I93: Immediate | J93: chandanagopal29@gmail.com | K93: 7618719963 | L93: M.com | M93: 1 Year | N93: Finlo Tax Inc. | O93: 3 LPA | R93: 3.5 LPA | S93: Sourced | T93: Portal-LinkedIN | U93: 46034 | V93: 46034
A94: E005 | B94: R004 | C94: =IF(ISBLANK(B94),"",_xlfn.XLOOKUP(B94,Recruiter!A:A,Recruiter!B:B)) -> Pooja | D94: =IF(ISBLANK(A94),"",_xlfn.XLOOKUP(A94,'Requirement Overview'!C:C,'Requirement Overview'!E:E)) -> Talme | E94: =IF(ISBLANK(A94),"",_xlfn.XLOOKUP(A94,'Requirement Overview'!C:C,'Requirement Overview'!H:H)) -> Non - IT | F94: Key Account Manager | G94: =IF(ISBLANK(A94),"",_xlfn.XLOOKUP(A94,'Requirement Overview'!C:C,'Requirement Overview'!G:G)) -> Avinashi Ads | H94: Gowtham K M | J94: gowthamkm77@gmail.com | K94: 9035445936 | S94: Screening reject by HR | U94: 46034 | V94: 46034
A95: E005 | B95: R004 | C95: =IF(ISBLANK(B95),"",_xlfn.XLOOKUP(B95,Recruiter!A:A,Recruiter!B:B)) -> Pooja | D95: =IF(ISBLANK(A95),"",_xlfn.XLOOKUP(A95,'Requirement Overview'!C:C,'Requirement Overview'!E:E)) -> Talme | E95: =IF(ISBLANK(A95),"",_xlfn.XLOOKUP(A95,'Requirement Overview'!C:C,'Requirement Overview'!H:H)) -> Non - IT | F95: =IF(ISBLANK(A95),"",_xlfn.XLOOKUP(A95,'Requirement Overview'!C:C,'Requirement Overview'!I:I)) -> Key Accounts Manager | G95: =IF(ISBLANK(A95),"",_xlfn.XLOOKUP(A95,'Requirement Overview'!C:C,'Requirement Overview'!G:G)) -> Avinashi Ads | H95: Sridhar Patil | J95: sridharpatil4@gmail.com | K95: 9740326930 | S95: Screening reject by HR | U95: 46034 | V95: 46034
A96: E005 | B96: R004 | C96: =IF(ISBLANK(B96),"",_xlfn.XLOOKUP(B96,Recruiter!A:A,Recruiter!B:B)) -> Pooja | D96: =IF(ISBLANK(A96),"",_xlfn.XLOOKUP(A96,'Requirement Overview'!C:C,'Requirement Overview'!E:E)) -> Talme | E96: =IF(ISBLANK(A96),"",_xlfn.XLOOKUP(A96,'Requirement Overview'!C:C,'Requirement Overview'!H:H)) -> Non - IT | F96: =IF(ISBLANK(A96),"",_xlfn.XLOOKUP(A96,'Requirement Overview'!C:C,'Requirement Overview'!I:I)) -> Key Accounts Manager | G96: =IF(ISBLANK(A96),"",_xlfn.XLOOKUP(A96,'Requirement Overview'!C:C,'Requirement Overview'!G:G)) -> Avinashi Ads | H96: Goutham K G | K96: 8971264671 | S96: Not Interested job change | U96: 46034 | V96: 46034
A97: E005 | B97: R004 | C97: =IF(ISBLANK(B97),"",_xlfn.XLOOKUP(B97,Recruiter!A:A,Recruiter!B:B)) -> Pooja | D97: =IF(ISBLANK(A97),"",_xlfn.XLOOKUP(A97,'Requirement Overview'!C:C,'Requirement Overview'!E:E)) -> Talme | E97: =IF(ISBLANK(A97),"",_xlfn.XLOOKUP(A97,'Requirement Overview'!C:C,'Requirement Overview'!H:H)) -> Non - IT | F97: =IF(ISBLANK(A97),"",_xlfn.XLOOKUP(A97,'Requirement Overview'!C:C,'Requirement Overview'!I:I)) -> Key Accounts Manager | G97: =IF(ISBLANK(A97),"",_xlfn.XLOOKUP(A97,'Requirement Overview'!C:C,'Requirement Overview'!G:G)) -> Avinashi Ads | H97: Ashwin M.P | J97: 2018ashwin@gmail.com | K97: 9686840513 | S97: Not Interested job change | U97: 46034 | V97: 46034
A98: E005 | B98: R004 | C98: =IF(ISBLANK(B98),"",_xlfn.XLOOKUP(B98,Recruiter!A:A,Recruiter!B:B)) -> Pooja | D98: =IF(ISBLANK(A98),"",_xlfn.XLOOKUP(A98,'Requirement Overview'!C:C,'Requirement Overview'!E:E)) -> Talme | E98: =IF(ISBLANK(A98),"",_xlfn.XLOOKUP(A98,'Requirement Overview'!C:C,'Requirement Overview'!H:H)) -> Non - IT | F98: =IF(ISBLANK(A98),"",_xlfn.XLOOKUP(A98,'Requirement Overview'!C:C,'Requirement Overview'!I:I)) -> Key Accounts Manager | G98: =IF(ISBLANK(A98),"",_xlfn.XLOOKUP(A98,'Requirement Overview'!C:C,'Requirement Overview'!G:G)) -> Avinashi Ads | H98: Kartik.M.Kagadal. | J98: kagadalkathik@gmail.com | K98: 9535384449 | S98: Not Interested job change | U98: 46034 | V98: 46034
A99: D001 | B99: R003 | C99: =IF(ISBLANK(B99),"",_xlfn.XLOOKUP(B99,Recruiter!A:A,Recruiter!B:B)) -> Bhoomika | D99: =IF(ISBLANK(A99),"",_xlfn.XLOOKUP(A99,'Requirement Overview'!C:C,'Requirement Overview'!E:E)) -> Talme | E99: =IF(ISBLANK(A99),"",_xlfn.XLOOKUP(A99,'Requirement Overview'!C:C,'Requirement Overview'!H:H)) -> Non - IT | F99: =IF(ISBLANK(A99),"",_xlfn.XLOOKUP(A99,'Requirement Overview'!C:C,'Requirement Overview'!I:I)) -> Inside Sales Executive | G99: =IF(ISBLANK(A99),"",_xlfn.XLOOKUP(A99,'Requirement Overview'!C:C,'Requirement Overview'!G:G)) -> Peritas | H99: Shruthi CD | I99: Immediate | J99: shruthirajsk0@gmail.com | K99: 8050337578 | L99: B.E | M99: 1 years | N99: Apprentice | O99: 2.16 LPA | P99: Bengaluru | Q99: Bengaluru | R99: As per company standards | S99: Screening Reject by Client | T99: Portal-LinkedIN | U99: 46034 | V99: 46034
A100: H004 | B100: R004 | C100: =IF(ISBLANK(B100),"",_xlfn.XLOOKUP(B100,Recruiter!A:A,Recruiter!B:B)) -> Pooja | D100: =IF(ISBLANK(A100),"",_xlfn.XLOOKUP(A100,'Requirement Overview'!C:C,'Requirement Overview'!E:E)) -> Talme | E100: =IF(ISBLANK(A100),"",_xlfn.XLOOKUP(A100,'Requirement Overview'!C:C,'Requirement Overview'!H:H)) -> IT | F100: =IF(ISBLANK(A100),"",_xlfn.XLOOKUP(A100,'Requirement Overview'!C:C,'Requirement Overview'!I:I)) -> Lead Data Engineer | G100: =IF(ISBLANK(A100),"",_xlfn.XLOOKUP(A100,'Requirement Overview'!C:C,'Requirement Overview'!G:G)) -> Thoughtfocus | H100: D Nagarjuna | I100: Immediate | J100: derangulan227@gmail.com | K100: 7569309154 | L100: B.Com | M100: 11 Year | N100: Wipro | O100: 34 LPA | R100: 42 LPA | S100: Sourced | T100: Portal-Naukri | U100: 46035 | V100: 46035
...

Sheet Recruiter
A1: Recruiter ID | B1: Recruiter Name | C1: Email | D1: Phone Number | E1: Current Status | F1: Date of Joined | G1: LWD | H1: Designation
A2: R001 | B2: Harish | H2: HRBP
A3: R002 | B3: Harshitha | H3: Lead
A4: R003 | B4: Bhoomika | H4: Recruiter
A5: R004 | B5: Pooja | H5: Recruiter
A6: R005 | B6: Narthana | H6: Lead
A7: R006 | B7: Himanshu | H7: Recruiter
A8: R007 | B8: Pooja & Bhoomika

Sheet H. Role
A1: Position | B1: Harmonized Role
A2: Python Developer
A3: Lead Data Engineer
A4: Python Architect
A5: Windows system adminstrator
A6: Android BSP Developer
A7: Display driver
A8: Audio Driver
A9: Data Delivery Manager
A10: Senior IAM Operation Engineer
A11: Lead IAM Management
A12: PERL Developer
A13: Inside Sales Executive
... A26: Founder office assoicate

Sheet Performance Review
B2: Name | C2: No of Profiles as per Plan for the day | D2: No Of profile Shared | E2: Yet to receive feed back from panel | F2: No of profiles Screen Select | G2: No of Profiles rejected | H2: No of profiles in T1 | I2: T1 Rejected | L2: EMIDS | M2: ThoughtFocus | N2: Peritas | O2: Semnox | P2: Seralax | Q2: Inhouse | R2: KPIT | V2: Skill | W2: Open Positions | X2: Profiles
B3: Harshitha | C3: 75 | D3: 30 | E3: 5 | F3: 10 | G3: 20 | H3: 7 | I3: 3 | L3: 1. Windows sys - 18. 2. Python architech-13, | M3: 3.Lead Data - 5, DDM -2 | N3: Inside Sales - 2 | V3: Python Developer | W3: 2 | X3: Hold
B4: Bhoomika | C4: 75 | D4: 11 | E4: Nil | F4: 4 | G4: 7 | H4: 1 | I4: 2 | N4: Inside Sales - 5, Field - 2 | P4: BDE -2, | Q4: HR - 1 | U4: Emids | V4: Lead Data Engineer | W4: 4 | X4: Hold
B5: Pooja | C5: 60 | D5: 7 | E5: 2 | F5: 0 | G5: 5 | H5: 0 | I5: 0 | L5: Python Architect - 3 | R5: Android BSP - 4 | V5: Python Architect | W5: 1 | X5: 16
B6: Narthana | C6: 30 | D6: 7 | E6: 3 | F6: 0 | G6: 3 | H6: 0 | I6: 0 | L6: Winods system admin - 3 | R6: Android BSP - 4 | V6: Windows system adminstrator | W6: 1 | X6: 21
C7: =SUM(C3:C6) -> 240 | D7: =SUM(D3:D6) -> 55 | E7: =SUM(E3:E6) -> 10 | F7: =SUM(F3:F6) -> 14 | G7: =SUM(G3:G6) -> 35 | H7: =SUM(H3:H6) -> 8 | I7: =SUM(I3:I6) -> 5 | V7: Android BSP Developer | W7: 2 | X7: 8
C8: Naukri used- 321 | V8: Display driver | W8: 1 | X8: 0
V9: Audio Driver | W9: 1 | X9: 0
B15: Name | C15: No of Profiles as per Plan for the day | D15: No Of profile Shared | E15: Yet to receive feed back from panel | F15: No of profiles Screen Select | G15: No of Profiles rejected | H15: No of profiles in T1 | I15: T1 Rejected | L15: EMIDS | M15: ThoughtFocus | N15: Peritas | O15: Semnox | P15: Seralax | Q15: Inhouse | R15: KPIT | S15: Avinashi Ads
B16: Harshitha | C16: 20 | D16: 7 | E16: 4 | F16: 3 | H16: 3 | L16: 1. Windows sys - 3, Python architech-4
B17: Bhoomika | C17: 95 | D17: 25 | E17: 13 | F17: 5 | G17: 7 | H17: 4 | N17: Inside Sales - 6 | Q17: HR - 9 | S17: Graphic-2, Associate-1, KAM-4,Sales head-3
B18: Pooja | C18: 60 | D18: 20 | E18: 4 | F18: 1 | G18: 15 | H18: 0 | I18: 1 | M18: Lead data engineer-7 | S18: KAM-9, Associate sales-1, sales head-3
B19: Narthana | C19: 125 | D19: 19 | E19: 3 | F19: 5 | G19: 11 | H19: 5 | L19: Winods system admin - 17 | R19: Display driver-2
C20: =SUM(C16:C19) -> 300 | D20: =SUM(D16:D19) -> 71 | E20: =SUM(E16:E19) -> 24 | F20: =SUM(F16:F19) -> 14 | G20: =SUM(G16:G19) -> 33 | H20: =SUM(H16:H19) -> 12 | I20: =SUM(I16:I19) -> 1
B23: Name | C23: No of Profiles as per Plan for the day | D23: No Of profile Shared | E23: Yet to receive feed back from panel | F23: No of profiles Screen Select | G23: No of Profiles rejected | H23: No of profiles in T1 | I23: T1 Rejected | J23: IN T2 | K23: IN T3 | L23: EMIDS | M23: ThoughtFocus | N23: Peritas | O23: Semnox | P23: Seralax | Q23: Inhouse | R23: KPIT | S23: GNA | T23: Lead SOC | U23: Avinashi Ads
B24: Harshitha | C24: 80 | D24: 23 | E24: 3 | F24: 19 | G24: 3 | I24: 14 | J24: 1 | K24: 3 | L24: Wndows System - 5, Angular JS - 5, Python - 5 | M24: Lead Data engineer-3 | O24: .Net Dev -3 | T24: Angular RF Designer - 2
B25: Bhoomika | C25: 85 | D25: 23 | E25: 11 | G25: 6 | I25: 1 | L25: Angular JS - 6 | N25: Inside Sales - 7 | O25: Technical Lead Mobile -1 | U25: KAM - 4, Sales Head - 1, Associate Sales - 1, Graphic Designer -3
B26: Pooja | C26: 75 | D26: 31 | E26: 19 | G26: 4 | J26: 1 | L26: Angular JS - 4 | N26: Inside Sales - 3, Feild Sales -2 | O26: Technical Lead Mobile -1 | U26: Sales Head -11, GRaphic Designer -4, Associate Sales -2, KAM -1
B27: Narthana | C27: 85 | D27: 24 | E27: 5 | F27: 4 | H27: 2 | I27: 2 | L27: Windows system - 11, Python - 2 | M27: IAM Eng - 4. Lead IAM - 1 | O27: .Net Dev- 5 | S27: Block Chain Dev -1
C28: =SUM(C24:C27) -> 325 | D28: =SUM(D24:D27) -> 101 | E28: =SUM(E24:E27) -> 38 | F28: =SUM(F24:F27) -> 23 | G28: =SUM(G24:G27) -> 13 | H28: =SUM(H24:H27) -> 2 | I28: =SUM(I24:I27) -> 17
B34: RECRUITER | C34: REQUIREMENTS | D34: FROM 26-01-2026 TO 30-01-2026 | F34: Least No of Interviews should be scheduled in a day
B35: Harshitha | C35: EMIDS | D35: 3 Days | F35: Acheivable commitments
B36: Harshitha | C36: ThoughtFocus, KPIT, | F36: No of Profiles to be shared
B37: Pooja | C37: Vidita,Semnox, Peritas, Thoughtfocus
B38: Narthana | C38: ThoughtFocus, KPIT, Semnox, Peritas, EMIDS
B39: Bhoomika | C39: Vidita,Semnox, Peritas, Avinashi Ads
B42: Name | C42: No of Profiles as per Plan for the day | D42: No Of profile Shared | E42: Yet to receive feed back from panel | F42: No of profiles Screen Select | G42: No of Profiles rejected | H42: No of profiles in T1 | I42: T1 Rejected | J42: IN T2 | K42: IN T3 | L42: EMIDS | M42: ThoughtFocus | N42: Peritas | O42: Semnox | P42: Seralax | Q42: Inhouse | R42: KPIT | S42: Viditha | T42: Lead SOC | U42: Avinashi Ads
B43: Harshitha | C43: 60 | D43: 27 | E43: 6 | F43: 13 | G43: 8 | H43: 10 | I43: 2 | J43: 3 | L43: Java Sript -5, Python - 9, Angular JS- 1, Windows System -6 | M43: Java Lead support - 6
B44: Bhoomika | C44: 20 | D44: 18 | E44: 18 (Yet to share) | O44: .Net - 1 | S44: Full Stack Dev - 17
B45: Pooja | C45: 45 | D45: 18 | E45: 10 | N45: Inside Sales -7 | O45: .Net - 1 | S45: Full Stack Dev - 10
B46: Narthana | C46: 60 | D46: 24 | E46: 16 | G46: 3 | H46: 4 | J46: 1 | L46: Windows System -9, Python -2 | M46: Java Lead support - 2, IAM Eng-3, Senior IAM -1 | O46: Tech Lead -4 | S46: Full Stack Dev - 3
C47: =SUM(C43:C46) -> 185 | D47: =SUM(D43:D46) -> 87 | E47: =SUM(E43:E46) -> 32 | F47: =SUM(F43:F46) -> 13 | G47: =SUM(G43:G46) -> 11 | H47: =SUM(H43:H46) -> 14 | I47: =SUM(I43:I46) -> 2 | J47: =SUM(J43:J46) -> 4
B50: RECRUITER | C50: REQUIREMENTS, FROM 02-02-2026 TO 07-02-2026
B51: Harshitha | C51: EMIDS,ThoughtFocus, KPIT,GNA
B52: Pooja | C52: ,Semnox, Peritas, Thoughtfocus, GNA
B53: Narthana | C53: ThoughtFocus, KPIT, Semnox, GNA, EMIDS
B54: Bhoomika | C54: ,Semnox, Peritas, Avinashi Ads, GNA,
B57: Name | C57: No of Profiles as per Plan for the day | D57: No Of profile Shared | E57: Yet to receive feed back from panel | F57: No of profiles Screen Select | G57: No of Profiles rejected | H57: No of profiles in T1 | I57: T1 Rejected | J57: IN T2 | K57: IN T3 | L57: EMIDS | M57: ThoughtFocus | N57: Peritas | O57: Semnox | P57: GNA | Q57: KPIT | R57: Avinashi Ads
B58: Harshitha | C58: 40 | D58: 21 | E58: 8
B59: Bhoomika | C59: 55 | D59: 30 | H59: 2 | L59: Java Script - 6, Angular JS(1.7) - 2 | N59: Inside Sales- 10 | O59: Mobile Tech Lead -5 | P59: Full Stack Developer-5 | R59: Graphic Designer 1,Associate Sales -1
B60: Pooja | C60: 65 | D60: 30 | J60: 2 | M60: Java Lead support - 6 | N60: Inside Sales- 5 | O60: Mobile Tech Lead -4 | P60: QA Analyst - 13, full stack dev - 2
B61: Narthana | C61: 60 | D61: 28 | G61: 6 | H61: 3 | J61: 1 | M61: Java Lead support - 3 | O61: Mobile Tech Lead -4 | P61: QA Analyst - 8, Full stack dev - 9 | Q61: Display driver -4
C62: =SUM(C58:C61) -> 220 | D62: =SUM(D58:D61) -> 109 | E62: =SUM(E58:E61) -> 8 | F62: =SUM(F58:F61) -> 0 | G62: =SUM(G58:G61) -> 6 | H62: =SUM(H58:H61) -> 5 | I62: =SUM(I58:I61) -> 0 | J62: =SUM(J58:J61) -> 3
B64: RECRUITER | C64: REQUIREMENTS, FROM 09-02-2026 TO 13-02-2026
B65: Harshitha | C65: EMIDS,ThoughtFocus, KPIT,GNA, Brillio
B66: Harish | C66: GNA, Emergotec, Semnox, Brillio
B67: Pooja | C67: KPIT, Thoughtfocus, EMIDS, Semnox
B68: Narthana | C68: KPIT, Thoughtfocus, EMIDS
B69: Bhoomika | C69: Avinash ads, Peritas, GNA, Talme
B72: Name | C72: No of Profiles as per Plan for the day | D72: No Of profile Shared | E72: Yet to receive feed back from panel | F72: No of profiles Screen Select | G72: No of Profiles rejected | H72: No of profiles in T1 | I72: T1 Rejected | J72: IN T2 | K72: IN T3 | L72: EMIDS | M72: ThoughtFocus | N72: Peritas | O72: Megha Foods | P72: GNA | Q72: KPIT | R72: Avinashi Ads | S72: Semnox | T72: Anika Solutions
B73: Harshitha | C73: 68 | D73: 34 | E73: 13 | G73: 5 | H73: 1 | L73: Angular Js dev-2 | M73: Dats lead engineer- 4, Full stack-8, Backend developer-11, Frontend developer-9
B74: Bhoomika | C74: 45 | D74: 12 | H74: 2 | I74: 1 | N74: Inside Sales:2 | P74: Complaiance officer:1 | R74: Sales Head :9
B75: Pooja | C75: 75 | D75: 21 | H75: 1 | I75: 1 | J75: 1 | M75: Java Lead Support Analyst - 10 | N75: Inside Sales - 1 | O75: Sales Officer:1 | R75: Key Account Manager - 3 , Sales Head - 3 | S75: Mobile Tech Lead - 3
B76: Narthana | C76: 60 | D76: 20 | G76: 7 | H76: 2 | L76: Angular Js dev-4 | M76: Java lead Analyst-2, Lead data engr-1, Backend dev-3, Frontend dev-4 | O76: Sales Officer:1 | Q76: Display Driver-2, Android Bsp -1 | T76: Anika solution- Technical lead- 2
C77: =SUM(C73:C76) -> 248 | D77: =SUM(D73:D76) -> 87 | E77: =SUM(E73:E76) -> 13 | F77: =SUM(F73:F76) -> 0 | G77: =SUM(G73:G76) -> 12 | H77: =SUM(H73:H76) -> 6 | I77: =SUM(I73:I76) -> 2 | J77: =SUM(J73:J76) -> 1
B80: RECRUITER | C80: REQUIREMENTS,
B81: Harshitha
B82: Pooja
B83: Narthana
B84: Bhoomika
B87: 46074
B88: Name | C88: No of Profiles as per Plan for the day | D88: No Of profile Shared | E88: Yet to receive feed back from panel | F88: No of profiles Screen Select | G88: No of Profiles rejected | H88: No of profiles in T1 | I88: T1 Rejected | J88: IN T2 | K88: IN T3 | L88: EMIDS | M88: ThoughtFocus | N88: LTTS | O88: Megha Foods | P88: GNA | Q88: KPIT | R88: Avinashi Ads | S88: Peritas | T88: Anika Solutions
B89: Harshitha | C89: 53 | D89: 23 | E89: 16 | G89: 4 | I89: 1 | L89: Windows system admin-6 | M89: Full stack-2, Backend developer-5, Frontend developer-6 | N89: Electrical maintenance engineer-3
B90: Bhoomika | C90: 30 | D90: 15 | R90: Sales head-10, KAM-5
B91: Pooja | C91: 40 | D91: 15 | E91: 2 | F91: 8 | G91: 5 | R91: Key Account Manager - 6 , Sales Head - 6 | S91: Field sales-3
B92: Narthana | C92: 40 | D92: 18 | E92: 6 | F92: 3 | G92: 9 | H92: 5 | M92: JAVA lead analyst-1, Backend developer-6, Frontend-8 | T92: Technical lead-3
C93: 163 | D93: =SUM(D89:D92) -> 71 | E93: 24 | F93: 11 | G93: 18 | H93: 5 | I93: 1
B95: RECRUITER | C95: REQUIREMENTS, 23rd to 28th feb
B96: Harshitha | C96: Thought focus, Emids
B97: Pooja | C97: Avinashi ads, Thought focus, Anika solutions
B98: Narthana | C98: Anika solutions, Thought focus, Megha foods, Emids
B99: Bhoomika | C99: Avinashi ads, Peritas
B101: 46081
B102: Name | C102: No of Profiles as per Plan for the day | D102: No Of profile Shared | E102: Yet to receive feed back from panel | F102: No of profiles Screen Select | G102: No of Profiles rejected | H102: No of profiles in T1 | I102: T1 Rejected | J102: IN T2 | K102: IN T3 | L102: EMIDS | M102: ThoughtFocus | N102: LTTS | O102: Megha Foods | P102: GNA | Q102: KPIT | R102: Avinashi Ads | S102: Peritas | T102: Anika Solutions
B103: Harshitha | C103: 50 | D103: 15 | E103: 0 | F103: 6 | G103: 9 | H103: 4 | I103: 1 | L103: Windows system admin-13 | M103: Lead data engr-2
B104: Bhoomika | C104: 50 | D104: 15 | E104: 10 | F104: 2 | G104: 3 | H104: 0 | I104: 0 | R104: Sales head-5, KAM-3,Associate sales-2,Graphic designer-1 | S104: Field sales-4
B105: Pooja | C105: 45 | D105: 14 | E105: 9 | F105: 3 | G105: 2 | H105: 0 | I105: 0 | R105: Key Account Manager - 3 , Sales Head - 7,Associate sales-2 | S105: Inside sales-2
B106: Narthana | C106: 47 | D106: 5 | E106: 2 | F106: 2 | G106: 1 | H106: 1( Last week) | I106: 1(Last week) | J106: 2 (Last week) | M106: JAVA lead analyst-1 | O106: sales officer-1 | R106: Graphic designer-1 | T106: Technical lead-2
C107: 192 | D107: =SUM(D103:D106) -> 49 | E107: =SUM(E103:E106) -> 21 | F107: =SUM(F103:F106) -> 13 | G107: =SUM(G103:G106) -> 15 | H107: 4 | I107: 1 | J107: 2
B109: RECRUITER | C109: REQUIREMENTS, 23rd to 28th feb
B110: Harshitha
B111: Pooja
B112: Narthana
B113: Bhoomika
B116: 46088
B117: Name | C117: No of Profiles as per Plan for the day | D117: No Of profile Shared | E117: Yet to receive feed back from panel | F117: No of profiles Screen Select | G117: No of Profiles rejected | H117: No of profiles in T1 | I117: T1 Rejected | J117: IN T2 | K117: IN T3 | L117: EMIDS | M117: ThoughtFocus | N117: LTTS | O117: Megha Foods | P117: GNA | Q117: Micron | R117: Avinashi Ads | S117: Peritas | T117: Anika Solutions
B118: Harshitha | C118: 40 | D118: 12 | E118: 10 | G118: 2 | N118: HW Design-2 | Q118: Production operator-6, MFG_ITI-4
B119: Bhoomika | C119: 34 | D119: 6 | E119: 4 | G119: 2 | N119: PCB layout engineer-1, HW design engineer-1 | Q119: MFG_ITI-2 | R119: Associate sales-2
B120: Pooja | C120: 40 | D120: 6 | E120: 1 | G120: 5 | N120: HW design-4, PCB design-2
B121: Narthana
C122: 114 | D122: 24 | E122: 15 | F122: 4 | G122: 9
B125: 46095
B126: Name | C126: No of Profiles as per Plan for the day | D126: No Of profile Shared | E126: Yet to receive feed back from panel | F126: No of profiles Screen Select | G126: No of Profiles rejected | H126: No of profiles in T1 | I126: T1 Rejected | J126: IN T2 | K126: IN T3 | L126: EMIDS | M126: ThoughtFocus | N126: LTTS | O126: Megha Foods | P126: GNA | Q126: Micron | R126: Avinashi Ads | S126: Peritas | T126: Anika Solutions
B127: Harshitha | C127: 40 | D127: 16 | E127: 1 | F127: 8 | G127: 7 | H127: 7 | I127: 1 | L127: Windows system-1 | N127: HW Design-2, AI/ML-2 | Q127: MFG_ITI-5, Production operator-6
B128: Bhoomika | C128: 43 | D128: 10 | E128: 1 | G128: 1 | N128: Embedded SW developer-3 | Q128: Production Operator-7
B129: Pooja | C129: 50 | D129: 39 | E129: 0 | F129: 39 | G129: 0 | H129: 30 | I129: 9 | Q129: Production operator-22,MFG_ITI-17
B130: Narthana | C130: 50 | D130: 11 | E130: 3 | G130: 1 | H130: 7 | L130: windows system admin-2 | N130: Embedded Engineer-2 | O130: sales officer- 2 | Q130: Production operator-3,MFG_ITI-2
C131: 183 | D131: 76 | E131: 5 | F131: 47 | G131: 9 | H131: 44 | I131: 10
B134: 46102
B135: Name | C135: No of Profiles as per Plan for the day | D135: No Of profile Shared | E135: Yet to receive feed back from panel | F135: No of profiles Screen Select | G135: No of Profiles rejected | H135: No of profiles in T1 | I135: T1 Rejected | J135: IN T2 | K135: IN T3 | L135: EMIDS | M135: ThoughtFocus | N135: LTTS | O135: Megha Foods | P135: GNA | Q135: Micron | R135: Avinashi Ads | S135: Peritas | T135: Anika Solutions | U135: No of Joinings this month
...

Sheet Sheet5
A1: Sl.No | B1: Client | C1: Domain | D1: Position | E1: Comments | F1: Years of EXp | G1: Location
A2: 1 | B2: KPIT | C2: IT | D2: Android BSP Developer
A3: 2 | B3: KPIT | C3: IT | D3: Display driver
A4: 3 | B4: KPIT | C4: IT | D4: Audio Driver
A5: 4 | B5: Thoughtfocus | C5: IT | D5: Lead Data Engineer
A6: 5 | B6: Thoughtfocus | C6: IT | D6: Senior IAM Operation Engineer | E6: Sayiant, Entra ID & Azzure ID (Mandate) Immediate NP | F6: 6-9 Years
A7: 6 | B7: Thoughtfocus | C7: IT | D7: Lead IAM Management | E7: Sayiant, Entra ID & Azzure ID (Mandate) Immediate NP | F7: 6-9 Years
A8: 7 | B8: Thoughtfocus | C8: IT | D8: IAM Engineer Professionals
A9: 8 | B9: Thoughtfocus | C9: IT | D9: Java Lead Analyst | E9: Java/Python (Payment, Banking domain) & End to end card trans, supporting L1 and L3 | F9: 5+ Years
A10: 9 | B10: Peritas | C10: Non - IT | D10: Inside Sales Executive | E10: Exp in IT sales | F10: 1-2 Years
A11: 10 | B11: Peritas | C11: Non - IT | D11: Field Sales Executive
A12: 11 | B12: Avinashi Ads | C12: Non - IT | D12: Graphic Designer | E12: Yet to receive feedbak from client
A13: 12 | B13: Avinashi Ads | C13: Non - IT | D13: Sales Head | E13: Yet to receive feedbak from client
A14: 13 | B14: Avinashi Ads | C14: Non - IT | D14: Senior Sales Manager | E14: Yet to receive feedbak from client
A15: 14 | B15: Avinashi Ads | C15: Non - IT | D15: Associate Sales | E15: Yet to receive feedbak from client
A16: 15 | B16: Avinashi Ads | C16: Non - IT | D16: Key Accounts Manager | E16: Yet to receive feedbak from client
A17: 16 | B17: GNA | C17: Non - IT | D17: Compliance Officer
A18: 17 | B18: GNA | C18: Non - IT | D18: Lobby In Charge
A19: 18 | B19: GNA | C19: IT | D19: QA Analyst | E19: Mandate (bnking Domain), Autoation Testing tool | F19: 2-4 Years
A20: 19 | B20: GNA | C20: IT | D20: Full Stack Developer | E20: Angular, Node js | F20: 2-4 Years
A21: 20 | B21: EMIDS | C21: IT | D21: Java Script Developer | E21: Java script, HTML , CSS | F21: 4-8 Years | G21: C2H
A22: 21 | B22: SBI Project | C22: IT | D22: Oracle | E22: Golden Gate, CDC Integration, Cloud Era Archi, Oracle RDBMS, (Banking Domain) | F22: 10 Years | G22: Mumbai Location | H22: 14 LPA
A23: 22 | B23: Brillio | C23: IT | E23: AI, Machie Learning, DDM's
A24: 23 | B24: LTTs | C24: IT

Sheet Dropdowns
A1: Tech Status | C1: Offer Status | E1: Offer Accept Status | G1: Source | I1: Recruiters | K1: Joining Status | M1: Candidate current status | P1: Business unit | R1: Department | T1: Client | V1: Domain | X1: Priority | Z1: Position Current Status | AB1: Position | AD1: Type of Hire
A2: Select | C2: Offered Yet to Join | E2: Offer Accepted | G2: Portal-Naukri | I2: Harish | K2: Joined | M2: Sourced | P2: Talme | T2: GNA | V2: IT | X2: High | Z2: Open | AB2: Data Delivery Manager | AD2: New
A3: Reject | C3: Doccument Collection | E3: Offer Rejected | G3: Portal-LinkedIN | I3: Harshitha | K3: No Show | M3: Yet to Screen | T3: Thoughtfocus | V3: IT | X3: Medium | Z3: Offered | AB3: Android BSP Developer | AD3: Replacement
A4: Hold | C4: Offer Drop | G4: Employee Reference | I4: Bhoomika | K4: Drop after Offer Accept | M4: Screening Reject by Client | T4: EMIDS | V4: IT | X4: Low | Z4: Offer Stage | AB4: Display driver
A5: No Show | C5: Offer Stage Drop | G5: Campus Drive | I5: Pooja | M5: Tech 1 to be Scheduled | T5: KPIT | V5: IT | Z5: Closed | AB5: Audio Driver
I6: Narthana | M6: Tech 1 Awaiting Feedback | T6: Talme | V6: IT | Z6: Hold | AB6: Sales Head
I7: Himanshu | M7: Tech 1 Reject | T7: Peritas | V7: Non - IT | AB7: Senior Sales Manager
I8: Pooja & Bhoomika | M8: Tech 2 to be Scheduled | T8: Avinashi Ads | V8: Non - IT | AB8: Key Accounts Manager
M9: Tech 2 Awaiting Feedback | T9: Sarelx | V9: Non - IT | AB9: Associate Sales
M10: Tech 2 Reject | T10: LeadSOC | V10: IT | AB10: Graphic Designer
M11: Tech 3 to be Scheduled | T11: Semnox Solutions | V11: IT | AB11: Data Engineer
M12: Tech 3 Awaiting Feedback | T12: Prasanna Technologies | V12: IT | AB12: Lead Data Engineer
M13: Tech 3 Reject | T13: Viditha | V13: IT | AB13: Python Developer
M14: Yet to Offer | T14: Anika Solutions | V14: IT | AB14: EDIPECS Developer
M15: Offer Released | T15: Megha foods pvt ltd | V15: Non - IT | AB15: Web Designer
M16: Doccument Collection | T16: L&T | V16: IT | AB16: Blockchain Developer
M17: Offer Accepted Yet to Join | T17: LTTS | V17: IT | AB17: Compliance Officer
M18: Offer Rejected | T18: Micron | V18: IT | AB18: Optiva PLM Functional Consultant
M19: Joined | AB19: Technical Project Manager
M20: No Show | AB20: Senior IAM Operation Engineer
M21: Screening reject by HR | AB21: Lead IAM Management
M22: Not Interested job change | AB22: PERL Developer
M23: Awaiting feedback from client | AB23: Python Architect
M24: position closed | AB24: Windows system adminstrator
M25: Position on Hold | AB25: Inside Sales Executive
AB26: Field Sales Executive
AB27: Wiring Technicians
AB28: Lobby In Charge
AB29: Lobby In Charge
AB30: Business developement executive
AB31: Founder office assoicate
AB32: HR Recruiter
AB33: Analog RF Designer
AB34: Angular JS developer
AB35: IAM Engineer Professionals
AB36: .Net Backend Developer
AB37: .Net Developer - Contract Role
... AB75: Software Engineer

Sheet Sheet1
A2: Client | B2: Years of Exp | C2: Count of Client
B3: (blank) | C3: 24
A4: Total | C4: 24
A5: Avinashi Ads | B5: (blank) | C5: 13
B6: 8 Year | C6: 5
B7: 6 Year | C7: 4
B8: 1 Year | C8: 3
B9: Fresher | C9: 3
B10: 7 Years | C10: 2
B11: 5 Year | C11: 2
B12: 4 Years | C12: 2
B13: 10 Year | C13: 2
B14: 6 Months( Internship) | C14: 2
B15: 1 Years | C15: 2
B16: 9 Years | C16: 2
B17: 8 Years | C17: 2
... B45: 2 Years | C45: 1
A46: Avinashi Ads Total | C46: 72
A47: EMIDS | B47: 5 Years | C47: 11
B48: 6 Years | C48: 11
B49: 7 Years | C49: 7
B50: 9 Years | C50: 4
B51: 11 Years | C51: 4
B52: 14 Years | C52: 3
B53: 7.5 Years | C53: 3
B54: 5.3 Years | C54: 2
B55: 6.8 Years | C55: 2
B56: 10 Years | C56: 2
B57: 4.4 Years | C57: 2
B58: 5.2 Years | C58: 2
B59: 6.9 Years | C59: 2
... B88: 4+ Years | C88: 1
A89: EMIDS Total | C89: 95
A90: GNA | B90: 6 Years | C90: 1
A91: GNA Total | C91: 1
A92: KPIT | B92: (blank) | C92: 7
C93: 3
B94: 8 Years | C94: 1
B95: 6.5 Years | C95: 1
B96: 6 Years | C96: 1
B97: 12 | C97: 1
B98: 7.5 Years | C98: 1
B99: 9 Years | C99: 1
B100: 10.8 | C100: 1
B101: 6.8 | C101: 1
B102: 5.11 | C102: 1
B103: 11.5 Years | C103: 1
A104: KPIT Total | C104: 20
A105: LeadSOC | B105: 9 Years | C105: 1
B106: 12 Years | C106: 1
A107: LeadSOC Total | C107: 2
A108: Peritas | B108: (blank) | C108: 10
B109: 2 Years | C109: 2
B110: 1 Years | C110: 2
B111: 1.5 Years | C111: 2
B112: 4 Months | C112: 1
B113: 3 Years | C113: 1
B114: 2 Years ( Telesales) | C114: 1
B115: 1.2 Years | C115: 1
B116: 3.7 Years | C116: 1
B117: 1.3 Years | C117: 1
B118: 3 Year | C118: 1
B119: 1.4 Years | C119: 1
B120: 2.6 Years | C120: 1
... B131: 10 Months | C131: 1
A132: Peritas Total | C132: 36
A133: Saralx | B133: (blank) | C133: 6
B134: 1.5 Years | C134: 1
B135: 4 Years | C135: 1
A136: Saralx Total | C136: 8
A137: Sarelx | B137: 2 Year | C137: 1
B138: 3.5 Years | C138: 1
B139: 3 months | C139: 1
B140: 1.6 Year | C140: 1
B141: 1 Year | C141: 1
B142: 1.7 Year | C142: 1
A143: Sarelx Total | C143: 6
A144: Semnox Solutions | B144: 4 Years | C144: 3
B145: 4.4 Years | C145: 2
B146: 5.5 Years | C146: 1
B147: 4+ Years | C147: 1
B148: 6.11 Years | C148: 1
B149: 8 Year | C149: 1
B150: 5 Years | C150: 1
B151: 4.3 Years | C151: 1
B152: 5.6 Years | C152: 1
B153: 7 Years | C153: 1
B154: 12 Years | C154: 1
B155: 4 Year | C155: 1
B156: 4.6 Years | C156: 1
A157: Semnox Solutions Total | C157: 16
A158: Talme | B158: Fresher | C158: 9
B159: (blank) | C159: 6
B160: 1 Years | C160: 1
A161: Talme Total | C161: 16
A162: Thoughtfocus | B162: 14 Years | C162: 3
B163: 12 Years | C163: 2
B164: 8 Year | C164: 2
B165: 11 Year | C165: 2
B166: 4.7 Years | C166: 1
...

Sheet Sheet2
A2: Position | B2: Count of Job Id
A3: Windows system adminstrator | B3: 55
A4: Inside Sales Executive | B4: 31
A5: Sales Head | B5: 25
A6: Key Accounts Manager | B6: 21
A7: Angular JS developer | B7: 20
A8: Python Architect | B8: 20
A9: Android BSP Developer | B9: 18
A10: Graphic Designer | B10: 17
A11: HR Recruiter | B11: 16
A12: .Net Backend Developer | B12: 14
A13: Lead Data Engineer | B13: 13
A14: Business developement executive | B14: 12
... A28: Grand Total | B28: 295

Sheet Sheet3
A2: Client | B2: Count of Job Id
A3: EMIDS | B3: 95
A4: Avinashi Ads | B4: 72
A5: Peritas | B5: 36
A6: Thoughtfocus | B6: 23
A7: KPIT | B7: 20
A8: Semnox Solutions | B8: 16
A9: Talme | B9: 16
A10: Saralx | B10: 8
A11: Sarelx | B11: 6
A12: LeadSOC | B12: 2
A13: GNA | B13: 1
A15: Grand Total | B15: 295

Sheet Sheet4
